[
  {
    "total_energy_j": 909.32,
    "avg_power_w": 168.02,
    "max_power_w": 169.4,
    "duration_sec": 5.41,
    "samples": 109,
    "generation_time_sec": 5.44,
    "max_tokens": 256,
    "batch_size": 1,
    "per_query_energy_j": 909.32,
    "modality": "text_batched",
    "model": "Phi-3-mini-4k",
    "params_B": 3.8,
    "run": 1,
    "hardware": "NVIDIA H100 80GB HBM3",
    "backend": "cuda"
  },
  {
    "total_energy_j": 904.05,
    "avg_power_w": 166.94,
    "max_power_w": 169.24,
    "duration_sec": 5.42,
    "samples": 109,
    "generation_time_sec": 5.42,
    "max_tokens": 256,
    "batch_size": 1,
    "per_query_energy_j": 904.05,
    "modality": "text_batched",
    "model": "Phi-3-mini-4k",
    "params_B": 3.8,
    "run": 2,
    "hardware": "NVIDIA H100 80GB HBM3",
    "backend": "cuda"
  },
  {
    "total_energy_j": 889.82,
    "avg_power_w": 167.36,
    "max_power_w": 169.63,
    "duration_sec": 5.32,
    "samples": 107,
    "generation_time_sec": 5.37,
    "max_tokens": 256,
    "batch_size": 1,
    "per_query_energy_j": 889.82,
    "modality": "text_batched",
    "model": "Phi-3-mini-4k",
    "params_B": 3.8,
    "run": 3,
    "hardware": "NVIDIA H100 80GB HBM3",
    "backend": "cuda"
  },
  {
    "total_energy_j": 898.9,
    "avg_power_w": 166.04,
    "max_power_w": 167.5,
    "duration_sec": 5.41,
    "samples": 109,
    "generation_time_sec": 5.45,
    "max_tokens": 256,
    "batch_size": 1,
    "per_query_energy_j": 898.9,
    "modality": "text_batched",
    "model": "Phi-3-mini-4k",
    "params_B": 3.8,
    "run": 4,
    "hardware": "NVIDIA H100 80GB HBM3",
    "backend": "cuda"
  },
  {
    "total_energy_j": 875.85,
    "avg_power_w": 167.9,
    "max_power_w": 170.07,
    "duration_sec": 5.22,
    "samples": 105,
    "generation_time_sec": 5.26,
    "max_tokens": 256,
    "batch_size": 1,
    "per_query_energy_j": 875.85,
    "modality": "text_batched",
    "model": "Phi-3-mini-4k",
    "params_B": 3.8,
    "run": 5,
    "hardware": "NVIDIA H100 80GB HBM3",
    "backend": "cuda"
  },
  {
    "total_energy_j": 901.48,
    "avg_power_w": 166.47,
    "max_power_w": 168.01,
    "duration_sec": 5.42,
    "samples": 109,
    "generation_time_sec": 5.42,
    "max_tokens": 256,
    "batch_size": 1,
    "per_query_energy_j": 901.48,
    "modality": "text_batched",
    "model": "Phi-3-mini-4k",
    "params_B": 3.8,
    "run": 6,
    "hardware": "NVIDIA H100 80GB HBM3",
    "backend": "cuda"
  },
  {
    "total_energy_j": 885.15,
    "avg_power_w": 166.44,
    "max_power_w": 167.93,
    "duration_sec": 5.32,
    "samples": 107,
    "generation_time_sec": 5.34,
    "max_tokens": 256,
    "batch_size": 1,
    "per_query_energy_j": 885.15,
    "modality": "text_batched",
    "model": "Phi-3-mini-4k",
    "params_B": 3.8,
    "run": 7,
    "hardware": "NVIDIA H100 80GB HBM3",
    "backend": "cuda"
  },
  {
    "total_energy_j": 898.5,
    "avg_power_w": 165.88,
    "max_power_w": 169.18,
    "duration_sec": 5.42,
    "samples": 109,
    "generation_time_sec": 5.43,
    "max_tokens": 256,
    "batch_size": 1,
    "per_query_energy_j": 898.5,
    "modality": "text_batched",
    "model": "Phi-3-mini-4k",
    "params_B": 3.8,
    "run": 8,
    "hardware": "NVIDIA H100 80GB HBM3",
    "backend": "cuda"
  },
  {
    "total_energy_j": 879.99,
    "avg_power_w": 165.51,
    "max_power_w": 168.32,
    "duration_sec": 5.32,
    "samples": 107,
    "generation_time_sec": 5.34,
    "max_tokens": 256,
    "batch_size": 1,
    "per_query_energy_j": 879.99,
    "modality": "text_batched",
    "model": "Phi-3-mini-4k",
    "params_B": 3.8,
    "run": 9,
    "hardware": "NVIDIA H100 80GB HBM3",
    "backend": "cuda"
  },
  {
    "total_energy_j": 890.88,
    "avg_power_w": 166.05,
    "max_power_w": 167.79,
    "duration_sec": 5.37,
    "samples": 108,
    "generation_time_sec": 5.4,
    "max_tokens": 256,
    "batch_size": 1,
    "per_query_energy_j": 890.88,
    "modality": "text_batched",
    "model": "Phi-3-mini-4k",
    "params_B": 3.8,
    "run": 10,
    "hardware": "NVIDIA H100 80GB HBM3",
    "backend": "cuda"
  },
  {
    "total_energy_j": 887.28,
    "avg_power_w": 166.88,
    "max_power_w": 169.18,
    "duration_sec": 5.32,
    "samples": 107,
    "generation_time_sec": 5.36,
    "max_tokens": 256,
    "batch_size": 1,
    "per_query_energy_j": 887.28,
    "modality": "text_batched",
    "model": "Phi-3-mini-4k",
    "params_B": 3.8,
    "run": 11,
    "hardware": "NVIDIA H100 80GB HBM3",
    "backend": "cuda"
  },
  {
    "total_energy_j": 893.27,
    "avg_power_w": 164.92,
    "max_power_w": 167.59,
    "duration_sec": 5.42,
    "samples": 109,
    "generation_time_sec": 5.43,
    "max_tokens": 256,
    "batch_size": 1,
    "per_query_energy_j": 893.27,
    "modality": "text_batched",
    "model": "Phi-3-mini-4k",
    "params_B": 3.8,
    "run": 12,
    "hardware": "NVIDIA H100 80GB HBM3",
    "backend": "cuda"
  },
  {
    "total_energy_j": 889.58,
    "avg_power_w": 165.73,
    "max_power_w": 167.82,
    "duration_sec": 5.37,
    "samples": 108,
    "generation_time_sec": 5.37,
    "max_tokens": 256,
    "batch_size": 1,
    "per_query_energy_j": 889.58,
    "modality": "text_batched",
    "model": "Phi-3-mini-4k",
    "params_B": 3.8,
    "run": 13,
    "hardware": "NVIDIA H100 80GB HBM3",
    "backend": "cuda"
  },
  {
    "total_energy_j": 894.29,
    "avg_power_w": 165.09,
    "max_power_w": 167.96,
    "duration_sec": 5.42,
    "samples": 109,
    "generation_time_sec": 5.42,
    "max_tokens": 256,
    "batch_size": 1,
    "per_query_energy_j": 894.29,
    "modality": "text_batched",
    "model": "Phi-3-mini-4k",
    "params_B": 3.8,
    "run": 14,
    "hardware": "NVIDIA H100 80GB HBM3",
    "backend": "cuda"
  },
  {
    "total_energy_j": 884.49,
    "avg_power_w": 164.86,
    "max_power_w": 166.38,
    "duration_sec": 5.37,
    "samples": 108,
    "generation_time_sec": 5.39,
    "max_tokens": 256,
    "batch_size": 1,
    "per_query_energy_j": 884.49,
    "modality": "text_batched",
    "model": "Phi-3-mini-4k",
    "params_B": 3.8,
    "run": 15,
    "hardware": "NVIDIA H100 80GB HBM3",
    "backend": "cuda"
  },
  {
    "total_energy_j": 891.65,
    "avg_power_w": 164.61,
    "max_power_w": 166.76,
    "duration_sec": 5.42,
    "samples": 109,
    "generation_time_sec": 5.46,
    "max_tokens": 256,
    "batch_size": 1,
    "per_query_energy_j": 891.65,
    "modality": "text_batched",
    "model": "Phi-3-mini-4k",
    "params_B": 3.8,
    "run": 16,
    "hardware": "NVIDIA H100 80GB HBM3",
    "backend": "cuda"
  },
  {
    "total_energy_j": 873.32,
    "avg_power_w": 165.83,
    "max_power_w": 167.02,
    "duration_sec": 5.27,
    "samples": 106,
    "generation_time_sec": 5.28,
    "max_tokens": 256,
    "batch_size": 1,
    "per_query_energy_j": 873.32,
    "modality": "text_batched",
    "model": "Phi-3-mini-4k",
    "params_B": 3.8,
    "run": 17,
    "hardware": "NVIDIA H100 80GB HBM3",
    "backend": "cuda"
  },
  {
    "total_energy_j": 892.19,
    "avg_power_w": 164.71,
    "max_power_w": 167.36,
    "duration_sec": 5.42,
    "samples": 109,
    "generation_time_sec": 5.42,
    "max_tokens": 256,
    "batch_size": 1,
    "per_query_energy_j": 892.19,
    "modality": "text_batched",
    "model": "Phi-3-mini-4k",
    "params_B": 3.8,
    "run": 18,
    "hardware": "NVIDIA H100 80GB HBM3",
    "backend": "cuda"
  },
  {
    "total_energy_j": 863.87,
    "avg_power_w": 165.6,
    "max_power_w": 167.8,
    "duration_sec": 5.22,
    "samples": 105,
    "generation_time_sec": 5.27,
    "max_tokens": 256,
    "batch_size": 1,
    "per_query_energy_j": 863.87,
    "modality": "text_batched",
    "model": "Phi-3-mini-4k",
    "params_B": 3.8,
    "run": 19,
    "hardware": "NVIDIA H100 80GB HBM3",
    "backend": "cuda"
  },
  {
    "total_energy_j": 887.5,
    "avg_power_w": 165.38,
    "max_power_w": 167.06,
    "duration_sec": 5.37,
    "samples": 108,
    "generation_time_sec": 5.41,
    "max_tokens": 256,
    "batch_size": 1,
    "per_query_energy_j": 887.5,
    "modality": "text_batched",
    "model": "Phi-3-mini-4k",
    "params_B": 3.8,
    "run": 20,
    "hardware": "NVIDIA H100 80GB HBM3",
    "backend": "cuda"
  },
  {
    "total_energy_j": 910.18,
    "avg_power_w": 163.4,
    "max_power_w": 165.98,
    "duration_sec": 5.57,
    "samples": 112,
    "generation_time_sec": 5.58,
    "max_tokens": 256,
    "batch_size": 1,
    "per_query_energy_j": 910.18,
    "modality": "text_batched",
    "model": "Phi-3-mini-4k",
    "params_B": 3.8,
    "run": 21,
    "hardware": "NVIDIA H100 80GB HBM3",
    "backend": "cuda"
  },
  {
    "total_energy_j": 884.12,
    "avg_power_w": 164.73,
    "max_power_w": 167.61,
    "duration_sec": 5.37,
    "samples": 108,
    "generation_time_sec": 5.41,
    "max_tokens": 256,
    "batch_size": 1,
    "per_query_energy_j": 884.12,
    "modality": "text_batched",
    "model": "Phi-3-mini-4k",
    "params_B": 3.8,
    "run": 22,
    "hardware": "NVIDIA H100 80GB HBM3",
    "backend": "cuda"
  },
  {
    "total_energy_j": 878.34,
    "avg_power_w": 165.21,
    "max_power_w": 166.53,
    "duration_sec": 5.32,
    "samples": 107,
    "generation_time_sec": 5.34,
    "max_tokens": 256,
    "batch_size": 1,
    "per_query_energy_j": 878.34,
    "modality": "text_batched",
    "model": "Phi-3-mini-4k",
    "params_B": 3.8,
    "run": 23,
    "hardware": "NVIDIA H100 80GB HBM3",
    "backend": "cuda"
  },
  {
    "total_energy_j": 893.02,
    "avg_power_w": 164.87,
    "max_power_w": 166.82,
    "duration_sec": 5.42,
    "samples": 109,
    "generation_time_sec": 5.43,
    "max_tokens": 256,
    "batch_size": 1,
    "per_query_energy_j": 893.02,
    "modality": "text_batched",
    "model": "Phi-3-mini-4k",
    "params_B": 3.8,
    "run": 24,
    "hardware": "NVIDIA H100 80GB HBM3",
    "backend": "cuda"
  },
  {
    "total_energy_j": 885.21,
    "avg_power_w": 164.92,
    "max_power_w": 166.72,
    "duration_sec": 5.37,
    "samples": 108,
    "generation_time_sec": 5.39,
    "max_tokens": 256,
    "batch_size": 1,
    "per_query_energy_j": 885.21,
    "modality": "text_batched",
    "model": "Phi-3-mini-4k",
    "params_B": 3.8,
    "run": 25,
    "hardware": "NVIDIA H100 80GB HBM3",
    "backend": "cuda"
  },
  {
    "total_energy_j": 894.08,
    "avg_power_w": 163.6,
    "max_power_w": 166.96,
    "duration_sec": 5.47,
    "samples": 110,
    "generation_time_sec": 5.47,
    "max_tokens": 256,
    "batch_size": 1,
    "per_query_energy_j": 894.08,
    "modality": "text_batched",
    "model": "Phi-3-mini-4k",
    "params_B": 3.8,
    "run": 26,
    "hardware": "NVIDIA H100 80GB HBM3",
    "backend": "cuda"
  },
  {
    "total_energy_j": 881.55,
    "avg_power_w": 164.24,
    "max_power_w": 166.72,
    "duration_sec": 5.37,
    "samples": 108,
    "generation_time_sec": 5.4,
    "max_tokens": 256,
    "batch_size": 1,
    "per_query_energy_j": 881.55,
    "modality": "text_batched",
    "model": "Phi-3-mini-4k",
    "params_B": 3.8,
    "run": 27,
    "hardware": "NVIDIA H100 80GB HBM3",
    "backend": "cuda"
  },
  {
    "total_energy_j": 888.72,
    "avg_power_w": 164.1,
    "max_power_w": 165.7,
    "duration_sec": 5.42,
    "samples": 109,
    "generation_time_sec": 5.42,
    "max_tokens": 256,
    "batch_size": 1,
    "per_query_energy_j": 888.72,
    "modality": "text_batched",
    "model": "Phi-3-mini-4k",
    "params_B": 3.8,
    "run": 28,
    "hardware": "NVIDIA H100 80GB HBM3",
    "backend": "cuda"
  },
  {
    "total_energy_j": 871.71,
    "avg_power_w": 165.53,
    "max_power_w": 167.99,
    "duration_sec": 5.27,
    "samples": 106,
    "generation_time_sec": 5.27,
    "max_tokens": 256,
    "batch_size": 1,
    "per_query_energy_j": 871.71,
    "modality": "text_batched",
    "model": "Phi-3-mini-4k",
    "params_B": 3.8,
    "run": 29,
    "hardware": "NVIDIA H100 80GB HBM3",
    "backend": "cuda"
  },
  {
    "total_energy_j": 896.22,
    "avg_power_w": 163.96,
    "max_power_w": 167.38,
    "duration_sec": 5.47,
    "samples": 110,
    "generation_time_sec": 5.5,
    "max_tokens": 256,
    "batch_size": 1,
    "per_query_energy_j": 896.22,
    "modality": "text_batched",
    "model": "Phi-3-mini-4k",
    "params_B": 3.8,
    "run": 30,
    "hardware": "NVIDIA H100 80GB HBM3",
    "backend": "cuda"
  },
  {
    "total_energy_j": 910.82,
    "avg_power_w": 166.62,
    "max_power_w": 171.11,
    "duration_sec": 5.47,
    "samples": 110,
    "generation_time_sec": 5.48,
    "max_tokens": 256,
    "batch_size": 2,
    "per_query_energy_j": 455.41,
    "modality": "text_batched",
    "model": "Phi-3-mini-4k",
    "params_B": 3.8,
    "run": 1,
    "hardware": "NVIDIA H100 80GB HBM3",
    "backend": "cuda"
  },
  {
    "total_energy_j": 895.35,
    "avg_power_w": 166.89,
    "max_power_w": 171.63,
    "duration_sec": 5.37,
    "samples": 108,
    "generation_time_sec": 5.38,
    "max_tokens": 256,
    "batch_size": 2,
    "per_query_energy_j": 447.68,
    "modality": "text_batched",
    "model": "Phi-3-mini-4k",
    "params_B": 3.8,
    "run": 2,
    "hardware": "NVIDIA H100 80GB HBM3",
    "backend": "cuda"
  },
  {
    "total_energy_j": 893.36,
    "avg_power_w": 168.09,
    "max_power_w": 171.38,
    "duration_sec": 5.32,
    "samples": 107,
    "generation_time_sec": 5.32,
    "max_tokens": 256,
    "batch_size": 2,
    "per_query_energy_j": 446.68,
    "modality": "text_batched",
    "model": "Phi-3-mini-4k",
    "params_B": 3.8,
    "run": 3,
    "hardware": "NVIDIA H100 80GB HBM3",
    "backend": "cuda"
  },
  {
    "total_energy_j": 889.6,
    "avg_power_w": 167.32,
    "max_power_w": 170.52,
    "duration_sec": 5.32,
    "samples": 107,
    "generation_time_sec": 5.35,
    "max_tokens": 256,
    "batch_size": 2,
    "per_query_energy_j": 444.8,
    "modality": "text_batched",
    "model": "Phi-3-mini-4k",
    "params_B": 3.8,
    "run": 4,
    "hardware": "NVIDIA H100 80GB HBM3",
    "backend": "cuda"
  },
  {
    "total_energy_j": 887.38,
    "avg_power_w": 168.54,
    "max_power_w": 172.05,
    "duration_sec": 5.27,
    "samples": 106,
    "generation_time_sec": 5.29,
    "max_tokens": 256,
    "batch_size": 2,
    "per_query_energy_j": 443.69,
    "modality": "text_batched",
    "model": "Phi-3-mini-4k",
    "params_B": 3.8,
    "run": 5,
    "hardware": "NVIDIA H100 80GB HBM3",
    "backend": "cuda"
  },
  {
    "total_energy_j": 899.39,
    "avg_power_w": 167.58,
    "max_power_w": 170.63,
    "duration_sec": 5.37,
    "samples": 108,
    "generation_time_sec": 5.38,
    "max_tokens": 256,
    "batch_size": 2,
    "per_query_energy_j": 449.69,
    "modality": "text_batched",
    "model": "Phi-3-mini-4k",
    "params_B": 3.8,
    "run": 6,
    "hardware": "NVIDIA H100 80GB HBM3",
    "backend": "cuda"
  },
  {
    "total_energy_j": 893.09,
    "avg_power_w": 168.03,
    "max_power_w": 171.32,
    "duration_sec": 5.32,
    "samples": 107,
    "generation_time_sec": 5.32,
    "max_tokens": 256,
    "batch_size": 2,
    "per_query_energy_j": 446.55,
    "modality": "text_batched",
    "model": "Phi-3-mini-4k",
    "params_B": 3.8,
    "run": 7,
    "hardware": "NVIDIA H100 80GB HBM3",
    "backend": "cuda"
  },
  {
    "total_energy_j": 896.09,
    "avg_power_w": 166.92,
    "max_power_w": 170.15,
    "duration_sec": 5.37,
    "samples": 108,
    "generation_time_sec": 5.42,
    "max_tokens": 256,
    "batch_size": 2,
    "per_query_energy_j": 448.05,
    "modality": "text_batched",
    "model": "Phi-3-mini-4k",
    "params_B": 3.8,
    "run": 8,
    "hardware": "NVIDIA H100 80GB HBM3",
    "backend": "cuda"
  },
  {
    "total_energy_j": 904.1,
    "avg_power_w": 166.95,
    "max_power_w": 170.61,
    "duration_sec": 5.42,
    "samples": 109,
    "generation_time_sec": 5.43,
    "max_tokens": 256,
    "batch_size": 2,
    "per_query_energy_j": 452.05,
    "modality": "text_batched",
    "model": "Phi-3-mini-4k",
    "params_B": 3.8,
    "run": 9,
    "hardware": "NVIDIA H100 80GB HBM3",
    "backend": "cuda"
  },
  {
    "total_energy_j": 896.8,
    "avg_power_w": 167.16,
    "max_power_w": 170.61,
    "duration_sec": 5.37,
    "samples": 108,
    "generation_time_sec": 5.37,
    "max_tokens": 256,
    "batch_size": 2,
    "per_query_energy_j": 448.4,
    "modality": "text_batched",
    "model": "Phi-3-mini-4k",
    "params_B": 3.8,
    "run": 10,
    "hardware": "NVIDIA H100 80GB HBM3",
    "backend": "cuda"
  },
  {
    "total_energy_j": 902.37,
    "avg_power_w": 166.64,
    "max_power_w": 169.89,
    "duration_sec": 5.42,
    "samples": 109,
    "generation_time_sec": 5.43,
    "max_tokens": 256,
    "batch_size": 2,
    "per_query_energy_j": 451.19,
    "modality": "text_batched",
    "model": "Phi-3-mini-4k",
    "params_B": 3.8,
    "run": 11,
    "hardware": "NVIDIA H100 80GB HBM3",
    "backend": "cuda"
  },
  {
    "total_energy_j": 888.84,
    "avg_power_w": 167.19,
    "max_power_w": 171.29,
    "duration_sec": 5.32,
    "samples": 107,
    "generation_time_sec": 5.36,
    "max_tokens": 256,
    "batch_size": 2,
    "per_query_energy_j": 444.42,
    "modality": "text_batched",
    "model": "Phi-3-mini-4k",
    "params_B": 3.8,
    "run": 12,
    "hardware": "NVIDIA H100 80GB HBM3",
    "backend": "cuda"
  },
  {
    "total_energy_j": 901.18,
    "avg_power_w": 167.94,
    "max_power_w": 171.43,
    "duration_sec": 5.37,
    "samples": 108,
    "generation_time_sec": 5.38,
    "max_tokens": 256,
    "batch_size": 2,
    "per_query_energy_j": 450.59,
    "modality": "text_batched",
    "model": "Phi-3-mini-4k",
    "params_B": 3.8,
    "run": 13,
    "hardware": "NVIDIA H100 80GB HBM3",
    "backend": "cuda"
  },
  {
    "total_energy_j": 885.56,
    "avg_power_w": 168.18,
    "max_power_w": 173.29,
    "duration_sec": 5.27,
    "samples": 106,
    "generation_time_sec": 5.3,
    "max_tokens": 256,
    "batch_size": 2,
    "per_query_energy_j": 442.78,
    "modality": "text_batched",
    "model": "Phi-3-mini-4k",
    "params_B": 3.8,
    "run": 14,
    "hardware": "NVIDIA H100 80GB HBM3",
    "backend": "cuda"
  },
  {
    "total_energy_j": 901.72,
    "avg_power_w": 168.06,
    "max_power_w": 173.29,
    "duration_sec": 5.37,
    "samples": 108,
    "generation_time_sec": 5.38,
    "max_tokens": 256,
    "batch_size": 2,
    "per_query_energy_j": 450.86,
    "modality": "text_batched",
    "model": "Phi-3-mini-4k",
    "params_B": 3.8,
    "run": 15,
    "hardware": "NVIDIA H100 80GB HBM3",
    "backend": "cuda"
  },
  {
    "total_energy_j": 896.19,
    "avg_power_w": 167.04,
    "max_power_w": 172.1,
    "duration_sec": 5.37,
    "samples": 108,
    "generation_time_sec": 5.38,
    "max_tokens": 256,
    "batch_size": 2,
    "per_query_energy_j": 448.1,
    "modality": "text_batched",
    "model": "Phi-3-mini-4k",
    "params_B": 3.8,
    "run": 16,
    "hardware": "NVIDIA H100 80GB HBM3",
    "backend": "cuda"
  },
  {
    "total_energy_j": 893.88,
    "avg_power_w": 168.1,
    "max_power_w": 172.62,
    "duration_sec": 5.32,
    "samples": 107,
    "generation_time_sec": 5.32,
    "max_tokens": 256,
    "batch_size": 2,
    "per_query_energy_j": 446.94,
    "modality": "text_batched",
    "model": "Phi-3-mini-4k",
    "params_B": 3.8,
    "run": 17,
    "hardware": "NVIDIA H100 80GB HBM3",
    "backend": "cuda"
  },
  {
    "total_energy_j": 897.33,
    "avg_power_w": 167.21,
    "max_power_w": 172.62,
    "duration_sec": 5.37,
    "samples": 108,
    "generation_time_sec": 5.4,
    "max_tokens": 256,
    "batch_size": 2,
    "per_query_energy_j": 448.67,
    "modality": "text_batched",
    "model": "Phi-3-mini-4k",
    "params_B": 3.8,
    "run": 18,
    "hardware": "NVIDIA H100 80GB HBM3",
    "backend": "cuda"
  },
  {
    "total_energy_j": 900.77,
    "avg_power_w": 167.93,
    "max_power_w": 170.73,
    "duration_sec": 5.36,
    "samples": 108,
    "generation_time_sec": 5.37,
    "max_tokens": 256,
    "batch_size": 2,
    "per_query_energy_j": 450.38,
    "modality": "text_batched",
    "model": "Phi-3-mini-4k",
    "params_B": 3.8,
    "run": 19,
    "hardware": "NVIDIA H100 80GB HBM3",
    "backend": "cuda"
  },
  {
    "total_energy_j": 900.28,
    "avg_power_w": 167.72,
    "max_power_w": 170.0,
    "duration_sec": 5.37,
    "samples": 108,
    "generation_time_sec": 5.38,
    "max_tokens": 256,
    "batch_size": 2,
    "per_query_energy_j": 450.14,
    "modality": "text_batched",
    "model": "Phi-3-mini-4k",
    "params_B": 3.8,
    "run": 20,
    "hardware": "NVIDIA H100 80GB HBM3",
    "backend": "cuda"
  },
  {
    "total_energy_j": 921.48,
    "avg_power_w": 165.44,
    "max_power_w": 168.91,
    "duration_sec": 5.57,
    "samples": 112,
    "generation_time_sec": 5.59,
    "max_tokens": 256,
    "batch_size": 2,
    "per_query_energy_j": 460.74,
    "modality": "text_batched",
    "model": "Phi-3-mini-4k",
    "params_B": 3.8,
    "run": 21,
    "hardware": "NVIDIA H100 80GB HBM3",
    "backend": "cuda"
  },
  {
    "total_energy_j": 901.41,
    "avg_power_w": 167.97,
    "max_power_w": 170.85,
    "duration_sec": 5.37,
    "samples": 108,
    "generation_time_sec": 5.39,
    "max_tokens": 256,
    "batch_size": 2,
    "per_query_energy_j": 450.7,
    "modality": "text_batched",
    "model": "Phi-3-mini-4k",
    "params_B": 3.8,
    "run": 22,
    "hardware": "NVIDIA H100 80GB HBM3",
    "backend": "cuda"
  },
  {
    "total_energy_j": 905.03,
    "avg_power_w": 167.11,
    "max_power_w": 171.89,
    "duration_sec": 5.42,
    "samples": 109,
    "generation_time_sec": 5.45,
    "max_tokens": 256,
    "batch_size": 2,
    "per_query_energy_j": 452.51,
    "modality": "text_batched",
    "model": "Phi-3-mini-4k",
    "params_B": 3.8,
    "run": 23,
    "hardware": "NVIDIA H100 80GB HBM3",
    "backend": "cuda"
  },
  {
    "total_energy_j": 886.41,
    "avg_power_w": 168.36,
    "max_power_w": 171.88,
    "duration_sec": 5.27,
    "samples": 106,
    "generation_time_sec": 5.29,
    "max_tokens": 256,
    "batch_size": 2,
    "per_query_energy_j": 443.2,
    "modality": "text_batched",
    "model": "Phi-3-mini-4k",
    "params_B": 3.8,
    "run": 24,
    "hardware": "NVIDIA H100 80GB HBM3",
    "backend": "cuda"
  },
  {
    "total_energy_j": 889.19,
    "avg_power_w": 167.31,
    "max_power_w": 173.12,
    "duration_sec": 5.32,
    "samples": 107,
    "generation_time_sec": 5.34,
    "max_tokens": 256,
    "batch_size": 2,
    "per_query_energy_j": 444.6,
    "modality": "text_batched",
    "model": "Phi-3-mini-4k",
    "params_B": 3.8,
    "run": 25,
    "hardware": "NVIDIA H100 80GB HBM3",
    "backend": "cuda"
  },
  {
    "total_energy_j": 887.34,
    "avg_power_w": 168.52,
    "max_power_w": 173.57,
    "duration_sec": 5.27,
    "samples": 106,
    "generation_time_sec": 5.28,
    "max_tokens": 256,
    "batch_size": 2,
    "per_query_energy_j": 443.67,
    "modality": "text_batched",
    "model": "Phi-3-mini-4k",
    "params_B": 3.8,
    "run": 26,
    "hardware": "NVIDIA H100 80GB HBM3",
    "backend": "cuda"
  },
  {
    "total_energy_j": 899.89,
    "avg_power_w": 167.68,
    "max_power_w": 172.0,
    "duration_sec": 5.37,
    "samples": 108,
    "generation_time_sec": 5.42,
    "max_tokens": 256,
    "batch_size": 2,
    "per_query_energy_j": 449.94,
    "modality": "text_batched",
    "model": "Phi-3-mini-4k",
    "params_B": 3.8,
    "run": 27,
    "hardware": "NVIDIA H100 80GB HBM3",
    "backend": "cuda"
  },
  {
    "total_energy_j": 890.91,
    "avg_power_w": 169.2,
    "max_power_w": 171.41,
    "duration_sec": 5.27,
    "samples": 106,
    "generation_time_sec": 5.3,
    "max_tokens": 256,
    "batch_size": 2,
    "per_query_energy_j": 445.45,
    "modality": "text_batched",
    "model": "Phi-3-mini-4k",
    "params_B": 3.8,
    "run": 28,
    "hardware": "NVIDIA H100 80GB HBM3",
    "backend": "cuda"
  },
  {
    "total_energy_j": 898.37,
    "avg_power_w": 167.42,
    "max_power_w": 171.06,
    "duration_sec": 5.37,
    "samples": 108,
    "generation_time_sec": 5.41,
    "max_tokens": 256,
    "batch_size": 2,
    "per_query_energy_j": 449.19,
    "modality": "text_batched",
    "model": "Phi-3-mini-4k",
    "params_B": 3.8,
    "run": 29,
    "hardware": "NVIDIA H100 80GB HBM3",
    "backend": "cuda"
  },
  {
    "total_energy_j": 888.15,
    "avg_power_w": 168.66,
    "max_power_w": 171.35,
    "duration_sec": 5.27,
    "samples": 106,
    "generation_time_sec": 5.28,
    "max_tokens": 256,
    "batch_size": 2,
    "per_query_energy_j": 444.07,
    "modality": "text_batched",
    "model": "Phi-3-mini-4k",
    "params_B": 3.8,
    "run": 30,
    "hardware": "NVIDIA H100 80GB HBM3",
    "backend": "cuda"
  },
  {
    "total_energy_j": 919.98,
    "avg_power_w": 173.1,
    "max_power_w": 179.12,
    "duration_sec": 5.32,
    "samples": 107,
    "generation_time_sec": 5.33,
    "max_tokens": 256,
    "batch_size": 4,
    "per_query_energy_j": 230.0,
    "modality": "text_batched",
    "model": "Phi-3-mini-4k",
    "params_B": 3.8,
    "run": 1,
    "hardware": "NVIDIA H100 80GB HBM3",
    "backend": "cuda"
  },
  {
    "total_energy_j": 922.08,
    "avg_power_w": 171.87,
    "max_power_w": 178.69,
    "duration_sec": 5.37,
    "samples": 108,
    "generation_time_sec": 5.4,
    "max_tokens": 256,
    "batch_size": 4,
    "per_query_energy_j": 230.52,
    "modality": "text_batched",
    "model": "Phi-3-mini-4k",
    "params_B": 3.8,
    "run": 2,
    "hardware": "NVIDIA H100 80GB HBM3",
    "backend": "cuda"
  },
  {
    "total_energy_j": 928.52,
    "avg_power_w": 171.57,
    "max_power_w": 178.69,
    "duration_sec": 5.41,
    "samples": 109,
    "generation_time_sec": 5.43,
    "max_tokens": 256,
    "batch_size": 4,
    "per_query_energy_j": 232.13,
    "modality": "text_batched",
    "model": "Phi-3-mini-4k",
    "params_B": 3.8,
    "run": 3,
    "hardware": "NVIDIA H100 80GB HBM3",
    "backend": "cuda"
  },
  {
    "total_energy_j": 932.79,
    "avg_power_w": 170.73,
    "max_power_w": 176.53,
    "duration_sec": 5.47,
    "samples": 110,
    "generation_time_sec": 5.49,
    "max_tokens": 256,
    "batch_size": 4,
    "per_query_energy_j": 233.2,
    "modality": "text_batched",
    "model": "Phi-3-mini-4k",
    "params_B": 3.8,
    "run": 4,
    "hardware": "NVIDIA H100 80GB HBM3",
    "backend": "cuda"
  },
  {
    "total_energy_j": 914.13,
    "avg_power_w": 172.0,
    "max_power_w": 177.8,
    "duration_sec": 5.32,
    "samples": 107,
    "generation_time_sec": 5.34,
    "max_tokens": 256,
    "batch_size": 4,
    "per_query_energy_j": 228.53,
    "modality": "text_batched",
    "model": "Phi-3-mini-4k",
    "params_B": 3.8,
    "run": 5,
    "hardware": "NVIDIA H100 80GB HBM3",
    "backend": "cuda"
  },
  {
    "total_energy_j": 921.06,
    "avg_power_w": 171.65,
    "max_power_w": 177.73,
    "duration_sec": 5.37,
    "samples": 108,
    "generation_time_sec": 5.37,
    "max_tokens": 256,
    "batch_size": 4,
    "per_query_energy_j": 230.26,
    "modality": "text_batched",
    "model": "Phi-3-mini-4k",
    "params_B": 3.8,
    "run": 6,
    "hardware": "NVIDIA H100 80GB HBM3",
    "backend": "cuda"
  },
  {
    "total_energy_j": 935.15,
    "avg_power_w": 171.03,
    "max_power_w": 176.01,
    "duration_sec": 5.47,
    "samples": 110,
    "generation_time_sec": 5.47,
    "max_tokens": 256,
    "batch_size": 4,
    "per_query_energy_j": 233.79,
    "modality": "text_batched",
    "model": "Phi-3-mini-4k",
    "params_B": 3.8,
    "run": 7,
    "hardware": "NVIDIA H100 80GB HBM3",
    "backend": "cuda"
  },
  {
    "total_energy_j": 912.74,
    "avg_power_w": 171.73,
    "max_power_w": 175.8,
    "duration_sec": 5.32,
    "samples": 107,
    "generation_time_sec": 5.36,
    "max_tokens": 256,
    "batch_size": 4,
    "per_query_energy_j": 228.19,
    "modality": "text_batched",
    "model": "Phi-3-mini-4k",
    "params_B": 3.8,
    "run": 8,
    "hardware": "NVIDIA H100 80GB HBM3",
    "backend": "cuda"
  },
  {
    "total_energy_j": 920.33,
    "avg_power_w": 171.53,
    "max_power_w": 176.13,
    "duration_sec": 5.37,
    "samples": 108,
    "generation_time_sec": 5.37,
    "max_tokens": 256,
    "batch_size": 4,
    "per_query_energy_j": 230.08,
    "modality": "text_batched",
    "model": "Phi-3-mini-4k",
    "params_B": 3.8,
    "run": 9,
    "hardware": "NVIDIA H100 80GB HBM3",
    "backend": "cuda"
  },
  {
    "total_energy_j": 920.04,
    "avg_power_w": 171.56,
    "max_power_w": 176.28,
    "duration_sec": 5.36,
    "samples": 108,
    "generation_time_sec": 5.38,
    "max_tokens": 256,
    "batch_size": 4,
    "per_query_energy_j": 230.01,
    "modality": "text_batched",
    "model": "Phi-3-mini-4k",
    "params_B": 3.8,
    "run": 10,
    "hardware": "NVIDIA H100 80GB HBM3",
    "backend": "cuda"
  },
  {
    "total_energy_j": 916.04,
    "avg_power_w": 172.33,
    "max_power_w": 179.16,
    "duration_sec": 5.32,
    "samples": 107,
    "generation_time_sec": 5.35,
    "max_tokens": 256,
    "batch_size": 4,
    "per_query_energy_j": 229.01,
    "modality": "text_batched",
    "model": "Phi-3-mini-4k",
    "params_B": 3.8,
    "run": 11,
    "hardware": "NVIDIA H100 80GB HBM3",
    "backend": "cuda"
  },
  {
    "total_energy_j": 925.02,
    "avg_power_w": 172.42,
    "max_power_w": 178.99,
    "duration_sec": 5.37,
    "samples": 108,
    "generation_time_sec": 5.38,
    "max_tokens": 256,
    "batch_size": 4,
    "per_query_energy_j": 231.25,
    "modality": "text_batched",
    "model": "Phi-3-mini-4k",
    "params_B": 3.8,
    "run": 12,
    "hardware": "NVIDIA H100 80GB HBM3",
    "backend": "cuda"
  },
  {
    "total_energy_j": 928.59,
    "avg_power_w": 169.9,
    "max_power_w": 176.54,
    "duration_sec": 5.47,
    "samples": 110,
    "generation_time_sec": 5.51,
    "max_tokens": 256,
    "batch_size": 4,
    "per_query_energy_j": 232.15,
    "modality": "text_batched",
    "model": "Phi-3-mini-4k",
    "params_B": 3.8,
    "run": 13,
    "hardware": "NVIDIA H100 80GB HBM3",
    "backend": "cuda"
  },
  {
    "total_energy_j": 925.29,
    "avg_power_w": 170.88,
    "max_power_w": 177.04,
    "duration_sec": 5.42,
    "samples": 109,
    "generation_time_sec": 5.43,
    "max_tokens": 256,
    "batch_size": 4,
    "per_query_energy_j": 231.32,
    "modality": "text_batched",
    "model": "Phi-3-mini-4k",
    "params_B": 3.8,
    "run": 14,
    "hardware": "NVIDIA H100 80GB HBM3",
    "backend": "cuda"
  },
  {
    "total_energy_j": 927.28,
    "avg_power_w": 171.24,
    "max_power_w": 175.38,
    "duration_sec": 5.42,
    "samples": 109,
    "generation_time_sec": 5.43,
    "max_tokens": 256,
    "batch_size": 4,
    "per_query_energy_j": 231.82,
    "modality": "text_batched",
    "model": "Phi-3-mini-4k",
    "params_B": 3.8,
    "run": 15,
    "hardware": "NVIDIA H100 80GB HBM3",
    "backend": "cuda"
  },
  {
    "total_energy_j": 926.22,
    "avg_power_w": 171.08,
    "max_power_w": 175.36,
    "duration_sec": 5.41,
    "samples": 109,
    "generation_time_sec": 5.43,
    "max_tokens": 256,
    "batch_size": 4,
    "per_query_energy_j": 231.56,
    "modality": "text_batched",
    "model": "Phi-3-mini-4k",
    "params_B": 3.8,
    "run": 16,
    "hardware": "NVIDIA H100 80GB HBM3",
    "backend": "cuda"
  },
  {
    "total_energy_j": 919.47,
    "avg_power_w": 171.33,
    "max_power_w": 175.18,
    "duration_sec": 5.37,
    "samples": 108,
    "generation_time_sec": 5.39,
    "max_tokens": 256,
    "batch_size": 4,
    "per_query_energy_j": 229.87,
    "modality": "text_batched",
    "model": "Phi-3-mini-4k",
    "params_B": 3.8,
    "run": 17,
    "hardware": "NVIDIA H100 80GB HBM3",
    "backend": "cuda"
  },
  {
    "total_energy_j": 919.62,
    "avg_power_w": 171.41,
    "max_power_w": 175.03,
    "duration_sec": 5.37,
    "samples": 108,
    "generation_time_sec": 5.37,
    "max_tokens": 256,
    "batch_size": 4,
    "per_query_energy_j": 229.91,
    "modality": "text_batched",
    "model": "Phi-3-mini-4k",
    "params_B": 3.8,
    "run": 18,
    "hardware": "NVIDIA H100 80GB HBM3",
    "backend": "cuda"
  },
  {
    "total_energy_j": 951.63,
    "avg_power_w": 169.4,
    "max_power_w": 175.03,
    "duration_sec": 5.62,
    "samples": 113,
    "generation_time_sec": 5.65,
    "max_tokens": 256,
    "batch_size": 4,
    "per_query_energy_j": 237.91,
    "modality": "text_batched",
    "model": "Phi-3-mini-4k",
    "params_B": 3.8,
    "run": 19,
    "hardware": "NVIDIA H100 80GB HBM3",
    "backend": "cuda"
  },
  {
    "total_energy_j": 909.81,
    "avg_power_w": 171.18,
    "max_power_w": 177.12,
    "duration_sec": 5.32,
    "samples": 107,
    "generation_time_sec": 5.36,
    "max_tokens": 256,
    "batch_size": 4,
    "per_query_energy_j": 227.45,
    "modality": "text_batched",
    "model": "Phi-3-mini-4k",
    "params_B": 3.8,
    "run": 20,
    "hardware": "NVIDIA H100 80GB HBM3",
    "backend": "cuda"
  },
  {
    "total_energy_j": 933.33,
    "avg_power_w": 172.31,
    "max_power_w": 177.7,
    "duration_sec": 5.42,
    "samples": 109,
    "generation_time_sec": 5.43,
    "max_tokens": 256,
    "batch_size": 4,
    "per_query_energy_j": 233.33,
    "modality": "text_batched",
    "model": "Phi-3-mini-4k",
    "params_B": 3.8,
    "run": 21,
    "hardware": "NVIDIA H100 80GB HBM3",
    "backend": "cuda"
  },
  {
    "total_energy_j": 909.74,
    "avg_power_w": 171.19,
    "max_power_w": 175.28,
    "duration_sec": 5.32,
    "samples": 107,
    "generation_time_sec": 5.35,
    "max_tokens": 256,
    "batch_size": 4,
    "per_query_energy_j": 227.44,
    "modality": "text_batched",
    "model": "Phi-3-mini-4k",
    "params_B": 3.8,
    "run": 22,
    "hardware": "NVIDIA H100 80GB HBM3",
    "backend": "cuda"
  },
  {
    "total_energy_j": 931.79,
    "avg_power_w": 172.0,
    "max_power_w": 177.5,
    "duration_sec": 5.42,
    "samples": 109,
    "generation_time_sec": 5.43,
    "max_tokens": 256,
    "batch_size": 4,
    "per_query_energy_j": 232.95,
    "modality": "text_batched",
    "model": "Phi-3-mini-4k",
    "params_B": 3.8,
    "run": 23,
    "hardware": "NVIDIA H100 80GB HBM3",
    "backend": "cuda"
  },
  {
    "total_energy_j": 933.91,
    "avg_power_w": 170.9,
    "max_power_w": 176.25,
    "duration_sec": 5.47,
    "samples": 110,
    "generation_time_sec": 5.48,
    "max_tokens": 256,
    "batch_size": 4,
    "per_query_energy_j": 233.48,
    "modality": "text_batched",
    "model": "Phi-3-mini-4k",
    "params_B": 3.8,
    "run": 24,
    "hardware": "NVIDIA H100 80GB HBM3",
    "backend": "cuda"
  },
  {
    "total_energy_j": 918.22,
    "avg_power_w": 171.15,
    "max_power_w": 177.71,
    "duration_sec": 5.37,
    "samples": 108,
    "generation_time_sec": 5.37,
    "max_tokens": 256,
    "batch_size": 4,
    "per_query_energy_j": 229.56,
    "modality": "text_batched",
    "model": "Phi-3-mini-4k",
    "params_B": 3.8,
    "run": 25,
    "hardware": "NVIDIA H100 80GB HBM3",
    "backend": "cuda"
  },
  {
    "total_energy_j": 916.23,
    "avg_power_w": 170.82,
    "max_power_w": 178.5,
    "duration_sec": 5.37,
    "samples": 108,
    "generation_time_sec": 5.4,
    "max_tokens": 256,
    "batch_size": 4,
    "per_query_energy_j": 229.06,
    "modality": "text_batched",
    "model": "Phi-3-mini-4k",
    "params_B": 3.8,
    "run": 26,
    "hardware": "NVIDIA H100 80GB HBM3",
    "backend": "cuda"
  },
  {
    "total_energy_j": 918.19,
    "avg_power_w": 172.74,
    "max_power_w": 178.5,
    "duration_sec": 5.32,
    "samples": 107,
    "generation_time_sec": 5.36,
    "max_tokens": 256,
    "batch_size": 4,
    "per_query_energy_j": 229.55,
    "modality": "text_batched",
    "model": "Phi-3-mini-4k",
    "params_B": 3.8,
    "run": 27,
    "hardware": "NVIDIA H100 80GB HBM3",
    "backend": "cuda"
  },
  {
    "total_energy_j": 921.95,
    "avg_power_w": 171.82,
    "max_power_w": 178.25,
    "duration_sec": 5.37,
    "samples": 108,
    "generation_time_sec": 5.39,
    "max_tokens": 256,
    "batch_size": 4,
    "per_query_energy_j": 230.49,
    "modality": "text_batched",
    "model": "Phi-3-mini-4k",
    "params_B": 3.8,
    "run": 28,
    "hardware": "NVIDIA H100 80GB HBM3",
    "backend": "cuda"
  },
  {
    "total_energy_j": 922.77,
    "avg_power_w": 172.06,
    "max_power_w": 176.15,
    "duration_sec": 5.36,
    "samples": 108,
    "generation_time_sec": 5.37,
    "max_tokens": 256,
    "batch_size": 4,
    "per_query_energy_j": 230.69,
    "modality": "text_batched",
    "model": "Phi-3-mini-4k",
    "params_B": 3.8,
    "run": 29,
    "hardware": "NVIDIA H100 80GB HBM3",
    "backend": "cuda"
  },
  {
    "total_energy_j": 920.95,
    "avg_power_w": 170.05,
    "max_power_w": 176.38,
    "duration_sec": 5.42,
    "samples": 109,
    "generation_time_sec": 5.46,
    "max_tokens": 256,
    "batch_size": 4,
    "per_query_energy_j": 230.24,
    "modality": "text_batched",
    "model": "Phi-3-mini-4k",
    "params_B": 3.8,
    "run": 30,
    "hardware": "NVIDIA H100 80GB HBM3",
    "backend": "cuda"
  },
  {
    "total_energy_j": 982.15,
    "avg_power_w": 183.15,
    "max_power_w": 195.71,
    "duration_sec": 5.37,
    "samples": 108,
    "generation_time_sec": 5.4,
    "max_tokens": 256,
    "batch_size": 8,
    "per_query_energy_j": 122.77,
    "modality": "text_batched",
    "model": "Phi-3-mini-4k",
    "params_B": 3.8,
    "run": 1,
    "hardware": "NVIDIA H100 80GB HBM3",
    "backend": "cuda"
  },
  {
    "total_energy_j": 979.28,
    "avg_power_w": 184.28,
    "max_power_w": 196.3,
    "duration_sec": 5.32,
    "samples": 107,
    "generation_time_sec": 5.33,
    "max_tokens": 256,
    "batch_size": 8,
    "per_query_energy_j": 122.41,
    "modality": "text_batched",
    "model": "Phi-3-mini-4k",
    "params_B": 3.8,
    "run": 2,
    "hardware": "NVIDIA H100 80GB HBM3",
    "backend": "cuda"
  },
  {
    "total_energy_j": 978.44,
    "avg_power_w": 182.51,
    "max_power_w": 195.74,
    "duration_sec": 5.36,
    "samples": 108,
    "generation_time_sec": 5.39,
    "max_tokens": 256,
    "batch_size": 8,
    "per_query_energy_j": 122.31,
    "modality": "text_batched",
    "model": "Phi-3-mini-4k",
    "params_B": 3.8,
    "run": 3,
    "hardware": "NVIDIA H100 80GB HBM3",
    "backend": "cuda"
  },
  {
    "total_energy_j": 980.04,
    "avg_power_w": 182.7,
    "max_power_w": 196.45,
    "duration_sec": 5.37,
    "samples": 108,
    "generation_time_sec": 5.41,
    "max_tokens": 256,
    "batch_size": 8,
    "per_query_energy_j": 122.5,
    "modality": "text_batched",
    "model": "Phi-3-mini-4k",
    "params_B": 3.8,
    "run": 4,
    "hardware": "NVIDIA H100 80GB HBM3",
    "backend": "cuda"
  },
  {
    "total_energy_j": 998.51,
    "avg_power_w": 181.12,
    "max_power_w": 195.19,
    "duration_sec": 5.52,
    "samples": 111,
    "generation_time_sec": 5.52,
    "max_tokens": 256,
    "batch_size": 8,
    "per_query_energy_j": 124.81,
    "modality": "text_batched",
    "model": "Phi-3-mini-4k",
    "params_B": 3.8,
    "run": 5,
    "hardware": "NVIDIA H100 80GB HBM3",
    "backend": "cuda"
  },
  {
    "total_energy_j": 974.65,
    "avg_power_w": 183.41,
    "max_power_w": 195.34,
    "duration_sec": 5.32,
    "samples": 107,
    "generation_time_sec": 5.33,
    "max_tokens": 256,
    "batch_size": 8,
    "per_query_energy_j": 121.83,
    "modality": "text_batched",
    "model": "Phi-3-mini-4k",
    "params_B": 3.8,
    "run": 6,
    "hardware": "NVIDIA H100 80GB HBM3",
    "backend": "cuda"
  },
  {
    "total_energy_j": 986.93,
    "avg_power_w": 182.31,
    "max_power_w": 195.34,
    "duration_sec": 5.42,
    "samples": 109,
    "generation_time_sec": 5.42,
    "max_tokens": 256,
    "batch_size": 8,
    "per_query_energy_j": 123.37,
    "modality": "text_batched",
    "model": "Phi-3-mini-4k",
    "params_B": 3.8,
    "run": 7,
    "hardware": "NVIDIA H100 80GB HBM3",
    "backend": "cuda"
  },
  {
    "total_energy_j": 967.57,
    "avg_power_w": 183.84,
    "max_power_w": 196.0,
    "duration_sec": 5.27,
    "samples": 106,
    "generation_time_sec": 5.29,
    "max_tokens": 256,
    "batch_size": 8,
    "per_query_energy_j": 120.95,
    "modality": "text_batched",
    "model": "Phi-3-mini-4k",
    "params_B": 3.8,
    "run": 8,
    "hardware": "NVIDIA H100 80GB HBM3",
    "backend": "cuda"
  },
  {
    "total_energy_j": 981.8,
    "avg_power_w": 183.09,
    "max_power_w": 196.0,
    "duration_sec": 5.37,
    "samples": 108,
    "generation_time_sec": 5.41,
    "max_tokens": 256,
    "batch_size": 8,
    "per_query_energy_j": 122.72,
    "modality": "text_batched",
    "model": "Phi-3-mini-4k",
    "params_B": 3.8,
    "run": 9,
    "hardware": "NVIDIA H100 80GB HBM3",
    "backend": "cuda"
  },
  {
    "total_energy_j": 969.51,
    "avg_power_w": 184.19,
    "max_power_w": 193.13,
    "duration_sec": 5.27,
    "samples": 106,
    "generation_time_sec": 5.29,
    "max_tokens": 256,
    "batch_size": 8,
    "per_query_energy_j": 121.19,
    "modality": "text_batched",
    "model": "Phi-3-mini-4k",
    "params_B": 3.8,
    "run": 10,
    "hardware": "NVIDIA H100 80GB HBM3",
    "backend": "cuda"
  },
  {
    "total_energy_j": 994.7,
    "avg_power_w": 182.06,
    "max_power_w": 193.13,
    "duration_sec": 5.47,
    "samples": 110,
    "generation_time_sec": 5.51,
    "max_tokens": 256,
    "batch_size": 8,
    "per_query_energy_j": 124.34,
    "modality": "text_batched",
    "model": "Phi-3-mini-4k",
    "params_B": 3.8,
    "run": 11,
    "hardware": "NVIDIA H100 80GB HBM3",
    "backend": "cuda"
  },
  {
    "total_energy_j": 974.36,
    "avg_power_w": 183.49,
    "max_power_w": 195.5,
    "duration_sec": 5.31,
    "samples": 107,
    "generation_time_sec": 5.34,
    "max_tokens": 256,
    "batch_size": 8,
    "per_query_energy_j": 121.8,
    "modality": "text_batched",
    "model": "Phi-3-mini-4k",
    "params_B": 3.8,
    "run": 12,
    "hardware": "NVIDIA H100 80GB HBM3",
    "backend": "cuda"
  },
  {
    "total_energy_j": 1001.74,
    "avg_power_w": 181.8,
    "max_power_w": 195.5,
    "duration_sec": 5.51,
    "samples": 111,
    "generation_time_sec": 5.53,
    "max_tokens": 256,
    "batch_size": 8,
    "per_query_energy_j": 125.22,
    "modality": "text_batched",
    "model": "Phi-3-mini-4k",
    "params_B": 3.8,
    "run": 13,
    "hardware": "NVIDIA H100 80GB HBM3",
    "backend": "cuda"
  },
  {
    "total_energy_j": 985.16,
    "avg_power_w": 182.06,
    "max_power_w": 194.96,
    "duration_sec": 5.41,
    "samples": 109,
    "generation_time_sec": 5.42,
    "max_tokens": 256,
    "batch_size": 8,
    "per_query_energy_j": 123.14,
    "modality": "text_batched",
    "model": "Phi-3-mini-4k",
    "params_B": 3.8,
    "run": 14,
    "hardware": "NVIDIA H100 80GB HBM3",
    "backend": "cuda"
  },
  {
    "total_energy_j": 1002.67,
    "avg_power_w": 181.96,
    "max_power_w": 194.96,
    "duration_sec": 5.51,
    "samples": 111,
    "generation_time_sec": 5.53,
    "max_tokens": 256,
    "batch_size": 8,
    "per_query_energy_j": 125.33,
    "modality": "text_batched",
    "model": "Phi-3-mini-4k",
    "params_B": 3.8,
    "run": 15,
    "hardware": "NVIDIA H100 80GB HBM3",
    "backend": "cuda"
  },
  {
    "total_energy_j": 991.56,
    "avg_power_w": 181.53,
    "max_power_w": 194.33,
    "duration_sec": 5.47,
    "samples": 110,
    "generation_time_sec": 5.49,
    "max_tokens": 256,
    "batch_size": 8,
    "per_query_energy_j": 123.94,
    "modality": "text_batched",
    "model": "Phi-3-mini-4k",
    "params_B": 3.8,
    "run": 16,
    "hardware": "NVIDIA H100 80GB HBM3",
    "backend": "cuda"
  },
  {
    "total_energy_j": 1005.39,
    "avg_power_w": 180.82,
    "max_power_w": 194.33,
    "duration_sec": 5.56,
    "samples": 112,
    "generation_time_sec": 5.6,
    "max_tokens": 256,
    "batch_size": 8,
    "per_query_energy_j": 125.67,
    "modality": "text_batched",
    "model": "Phi-3-mini-4k",
    "params_B": 3.8,
    "run": 17,
    "hardware": "NVIDIA H100 80GB HBM3",
    "backend": "cuda"
  },
  {
    "total_energy_j": 983.45,
    "avg_power_w": 183.4,
    "max_power_w": 196.24,
    "duration_sec": 5.37,
    "samples": 108,
    "generation_time_sec": 5.39,
    "max_tokens": 256,
    "batch_size": 8,
    "per_query_energy_j": 122.93,
    "modality": "text_batched",
    "model": "Phi-3-mini-4k",
    "params_B": 3.8,
    "run": 18,
    "hardware": "NVIDIA H100 80GB HBM3",
    "backend": "cuda"
  },
  {
    "total_energy_j": 994.67,
    "avg_power_w": 182.15,
    "max_power_w": 195.46,
    "duration_sec": 5.46,
    "samples": 110,
    "generation_time_sec": 5.48,
    "max_tokens": 256,
    "batch_size": 8,
    "per_query_energy_j": 124.33,
    "modality": "text_batched",
    "model": "Phi-3-mini-4k",
    "params_B": 3.8,
    "run": 19,
    "hardware": "NVIDIA H100 80GB HBM3",
    "backend": "cuda"
  },
  {
    "total_energy_j": 964.29,
    "avg_power_w": 183.28,
    "max_power_w": 197.05,
    "duration_sec": 5.26,
    "samples": 106,
    "generation_time_sec": 5.29,
    "max_tokens": 256,
    "batch_size": 8,
    "per_query_energy_j": 120.54,
    "modality": "text_batched",
    "model": "Phi-3-mini-4k",
    "params_B": 3.8,
    "run": 20,
    "hardware": "NVIDIA H100 80GB HBM3",
    "backend": "cuda"
  },
  {
    "total_energy_j": 988.85,
    "avg_power_w": 182.65,
    "max_power_w": 196.18,
    "duration_sec": 5.42,
    "samples": 109,
    "generation_time_sec": 5.42,
    "max_tokens": 256,
    "batch_size": 8,
    "per_query_energy_j": 123.61,
    "modality": "text_batched",
    "model": "Phi-3-mini-4k",
    "params_B": 3.8,
    "run": 21,
    "hardware": "NVIDIA H100 80GB HBM3",
    "backend": "cuda"
  },
  {
    "total_energy_j": 978.92,
    "avg_power_w": 182.51,
    "max_power_w": 195.12,
    "duration_sec": 5.37,
    "samples": 108,
    "generation_time_sec": 5.39,
    "max_tokens": 256,
    "batch_size": 8,
    "per_query_energy_j": 122.36,
    "modality": "text_batched",
    "model": "Phi-3-mini-4k",
    "params_B": 3.8,
    "run": 22,
    "hardware": "NVIDIA H100 80GB HBM3",
    "backend": "cuda"
  },
  {
    "total_energy_j": 975.57,
    "avg_power_w": 183.58,
    "max_power_w": 195.03,
    "duration_sec": 5.32,
    "samples": 107,
    "generation_time_sec": 5.35,
    "max_tokens": 256,
    "batch_size": 8,
    "per_query_energy_j": 121.95,
    "modality": "text_batched",
    "model": "Phi-3-mini-4k",
    "params_B": 3.8,
    "run": 23,
    "hardware": "NVIDIA H100 80GB HBM3",
    "backend": "cuda"
  },
  {
    "total_energy_j": 978.25,
    "avg_power_w": 182.43,
    "max_power_w": 197.74,
    "duration_sec": 5.37,
    "samples": 108,
    "generation_time_sec": 5.38,
    "max_tokens": 256,
    "batch_size": 8,
    "per_query_energy_j": 122.28,
    "modality": "text_batched",
    "model": "Phi-3-mini-4k",
    "params_B": 3.8,
    "run": 24,
    "hardware": "NVIDIA H100 80GB HBM3",
    "backend": "cuda"
  },
  {
    "total_energy_j": 985.49,
    "avg_power_w": 183.75,
    "max_power_w": 197.74,
    "duration_sec": 5.37,
    "samples": 108,
    "generation_time_sec": 5.4,
    "max_tokens": 256,
    "batch_size": 8,
    "per_query_energy_j": 123.19,
    "modality": "text_batched",
    "model": "Phi-3-mini-4k",
    "params_B": 3.8,
    "run": 25,
    "hardware": "NVIDIA H100 80GB HBM3",
    "backend": "cuda"
  },
  {
    "total_energy_j": 971.84,
    "avg_power_w": 182.91,
    "max_power_w": 197.46,
    "duration_sec": 5.32,
    "samples": 107,
    "generation_time_sec": 5.37,
    "max_tokens": 256,
    "batch_size": 8,
    "per_query_energy_j": 121.48,
    "modality": "text_batched",
    "model": "Phi-3-mini-4k",
    "params_B": 3.8,
    "run": 26,
    "hardware": "NVIDIA H100 80GB HBM3",
    "backend": "cuda"
  },
  {
    "total_energy_j": 979.52,
    "avg_power_w": 184.41,
    "max_power_w": 198.47,
    "duration_sec": 5.31,
    "samples": 107,
    "generation_time_sec": 5.33,
    "max_tokens": 256,
    "batch_size": 8,
    "per_query_energy_j": 122.44,
    "modality": "text_batched",
    "model": "Phi-3-mini-4k",
    "params_B": 3.8,
    "run": 27,
    "hardware": "NVIDIA H100 80GB HBM3",
    "backend": "cuda"
  },
  {
    "total_energy_j": 985.66,
    "avg_power_w": 182.08,
    "max_power_w": 197.02,
    "duration_sec": 5.42,
    "samples": 109,
    "generation_time_sec": 5.47,
    "max_tokens": 256,
    "batch_size": 8,
    "per_query_energy_j": 123.21,
    "modality": "text_batched",
    "model": "Phi-3-mini-4k",
    "params_B": 3.8,
    "run": 28,
    "hardware": "NVIDIA H100 80GB HBM3",
    "backend": "cuda"
  },
  {
    "total_energy_j": 974.8,
    "avg_power_w": 185.22,
    "max_power_w": 197.49,
    "duration_sec": 5.27,
    "samples": 106,
    "generation_time_sec": 5.27,
    "max_tokens": 256,
    "batch_size": 8,
    "per_query_energy_j": 121.85,
    "modality": "text_batched",
    "model": "Phi-3-mini-4k",
    "params_B": 3.8,
    "run": 29,
    "hardware": "NVIDIA H100 80GB HBM3",
    "backend": "cuda"
  },
  {
    "total_energy_j": 983.26,
    "avg_power_w": 181.56,
    "max_power_w": 194.21,
    "duration_sec": 5.42,
    "samples": 109,
    "generation_time_sec": 5.46,
    "max_tokens": 256,
    "batch_size": 8,
    "per_query_energy_j": 122.91,
    "modality": "text_batched",
    "model": "Phi-3-mini-4k",
    "params_B": 3.8,
    "run": 30,
    "hardware": "NVIDIA H100 80GB HBM3",
    "backend": "cuda"
  },
  {
    "total_energy_j": 1113.79,
    "avg_power_w": 202.15,
    "max_power_w": 227.19,
    "duration_sec": 5.52,
    "samples": 111,
    "generation_time_sec": 5.53,
    "max_tokens": 256,
    "batch_size": 16,
    "per_query_energy_j": 69.61,
    "modality": "text_batched",
    "model": "Phi-3-mini-4k",
    "params_B": 3.8,
    "run": 1,
    "hardware": "NVIDIA H100 80GB HBM3",
    "backend": "cuda"
  },
  {
    "total_energy_j": 1101.48,
    "avg_power_w": 205.49,
    "max_power_w": 228.59,
    "duration_sec": 5.37,
    "samples": 108,
    "generation_time_sec": 5.38,
    "max_tokens": 256,
    "batch_size": 16,
    "per_query_energy_j": 68.84,
    "modality": "text_batched",
    "model": "Phi-3-mini-4k",
    "params_B": 3.8,
    "run": 2,
    "hardware": "NVIDIA H100 80GB HBM3",
    "backend": "cuda"
  },
  {
    "total_energy_j": 1099.62,
    "avg_power_w": 205.26,
    "max_power_w": 232.49,
    "duration_sec": 5.36,
    "samples": 108,
    "generation_time_sec": 5.37,
    "max_tokens": 256,
    "batch_size": 16,
    "per_query_energy_j": 68.73,
    "modality": "text_batched",
    "model": "Phi-3-mini-4k",
    "params_B": 3.8,
    "run": 3,
    "hardware": "NVIDIA H100 80GB HBM3",
    "backend": "cuda"
  },
  {
    "total_energy_j": 1086.11,
    "avg_power_w": 206.46,
    "max_power_w": 232.49,
    "duration_sec": 5.27,
    "samples": 106,
    "generation_time_sec": 5.29,
    "max_tokens": 256,
    "batch_size": 16,
    "per_query_energy_j": 67.88,
    "modality": "text_batched",
    "model": "Phi-3-mini-4k",
    "params_B": 3.8,
    "run": 4,
    "hardware": "NVIDIA H100 80GB HBM3",
    "backend": "cuda"
  },
  {
    "total_energy_j": 1109.25,
    "avg_power_w": 203.17,
    "max_power_w": 230.41,
    "duration_sec": 5.47,
    "samples": 110,
    "generation_time_sec": 5.49,
    "max_tokens": 256,
    "batch_size": 16,
    "per_query_energy_j": 69.33,
    "modality": "text_batched",
    "model": "Phi-3-mini-4k",
    "params_B": 3.8,
    "run": 5,
    "hardware": "NVIDIA H100 80GB HBM3",
    "backend": "cuda"
  },
  {
    "total_energy_j": 1113.7,
    "avg_power_w": 204.08,
    "max_power_w": 230.33,
    "duration_sec": 5.46,
    "samples": 110,
    "generation_time_sec": 5.51,
    "max_tokens": 256,
    "batch_size": 16,
    "per_query_energy_j": 69.61,
    "modality": "text_batched",
    "model": "Phi-3-mini-4k",
    "params_B": 3.8,
    "run": 6,
    "hardware": "NVIDIA H100 80GB HBM3",
    "backend": "cuda"
  },
  {
    "total_energy_j": 1113.3,
    "avg_power_w": 203.94,
    "max_power_w": 229.31,
    "duration_sec": 5.46,
    "samples": 110,
    "generation_time_sec": 5.48,
    "max_tokens": 256,
    "batch_size": 16,
    "per_query_energy_j": 69.58,
    "modality": "text_batched",
    "model": "Phi-3-mini-4k",
    "params_B": 3.8,
    "run": 7,
    "hardware": "NVIDIA H100 80GB HBM3",
    "backend": "cuda"
  },
  {
    "total_energy_j": 1102.33,
    "avg_power_w": 203.84,
    "max_power_w": 230.29,
    "duration_sec": 5.41,
    "samples": 109,
    "generation_time_sec": 5.44,
    "max_tokens": 256,
    "batch_size": 16,
    "per_query_energy_j": 68.9,
    "modality": "text_batched",
    "model": "Phi-3-mini-4k",
    "params_B": 3.8,
    "run": 8,
    "hardware": "NVIDIA H100 80GB HBM3",
    "backend": "cuda"
  },
  {
    "total_energy_j": 1084.27,
    "avg_power_w": 206.1,
    "max_power_w": 228.71,
    "duration_sec": 5.27,
    "samples": 106,
    "generation_time_sec": 5.31,
    "max_tokens": 256,
    "batch_size": 16,
    "per_query_energy_j": 67.77,
    "modality": "text_batched",
    "model": "Phi-3-mini-4k",
    "params_B": 3.8,
    "run": 9,
    "hardware": "NVIDIA H100 80GB HBM3",
    "backend": "cuda"
  },
  {
    "total_energy_j": 1105.87,
    "avg_power_w": 206.37,
    "max_power_w": 231.77,
    "duration_sec": 5.36,
    "samples": 108,
    "generation_time_sec": 5.39,
    "max_tokens": 256,
    "batch_size": 16,
    "per_query_energy_j": 69.12,
    "modality": "text_batched",
    "model": "Phi-3-mini-4k",
    "params_B": 3.8,
    "run": 10,
    "hardware": "NVIDIA H100 80GB HBM3",
    "backend": "cuda"
  },
  {
    "total_energy_j": 1102.06,
    "avg_power_w": 205.68,
    "max_power_w": 229.0,
    "duration_sec": 5.36,
    "samples": 108,
    "generation_time_sec": 5.37,
    "max_tokens": 256,
    "batch_size": 16,
    "per_query_energy_j": 68.88,
    "modality": "text_batched",
    "model": "Phi-3-mini-4k",
    "params_B": 3.8,
    "run": 11,
    "hardware": "NVIDIA H100 80GB HBM3",
    "backend": "cuda"
  },
  {
    "total_energy_j": 1098.48,
    "avg_power_w": 205.05,
    "max_power_w": 228.75,
    "duration_sec": 5.36,
    "samples": 108,
    "generation_time_sec": 5.4,
    "max_tokens": 256,
    "batch_size": 16,
    "per_query_energy_j": 68.66,
    "modality": "text_batched",
    "model": "Phi-3-mini-4k",
    "params_B": 3.8,
    "run": 12,
    "hardware": "NVIDIA H100 80GB HBM3",
    "backend": "cuda"
  },
  {
    "total_energy_j": 1105.97,
    "avg_power_w": 206.47,
    "max_power_w": 235.06,
    "duration_sec": 5.36,
    "samples": 108,
    "generation_time_sec": 5.37,
    "max_tokens": 256,
    "batch_size": 16,
    "per_query_energy_j": 69.12,
    "modality": "text_batched",
    "model": "Phi-3-mini-4k",
    "params_B": 3.8,
    "run": 13,
    "hardware": "NVIDIA H100 80GB HBM3",
    "backend": "cuda"
  },
  {
    "total_energy_j": 1098.1,
    "avg_power_w": 206.9,
    "max_power_w": 235.06,
    "duration_sec": 5.31,
    "samples": 107,
    "generation_time_sec": 5.32,
    "max_tokens": 256,
    "batch_size": 16,
    "per_query_energy_j": 68.63,
    "modality": "text_batched",
    "model": "Phi-3-mini-4k",
    "params_B": 3.8,
    "run": 14,
    "hardware": "NVIDIA H100 80GB HBM3",
    "backend": "cuda"
  },
  {
    "total_energy_j": 1090.33,
    "avg_power_w": 205.4,
    "max_power_w": 231.98,
    "duration_sec": 5.31,
    "samples": 107,
    "generation_time_sec": 5.36,
    "max_tokens": 256,
    "batch_size": 16,
    "per_query_energy_j": 68.15,
    "modality": "text_batched",
    "model": "Phi-3-mini-4k",
    "params_B": 3.8,
    "run": 15,
    "hardware": "NVIDIA H100 80GB HBM3",
    "backend": "cuda"
  },
  {
    "total_energy_j": 1102.02,
    "avg_power_w": 205.63,
    "max_power_w": 231.53,
    "duration_sec": 5.37,
    "samples": 108,
    "generation_time_sec": 5.42,
    "max_tokens": 256,
    "batch_size": 16,
    "per_query_energy_j": 68.88,
    "modality": "text_batched",
    "model": "Phi-3-mini-4k",
    "params_B": 3.8,
    "run": 16,
    "hardware": "NVIDIA H100 80GB HBM3",
    "backend": "cuda"
  },
  {
    "total_energy_j": 1092.79,
    "avg_power_w": 205.89,
    "max_power_w": 235.28,
    "duration_sec": 5.31,
    "samples": 107,
    "generation_time_sec": 5.36,
    "max_tokens": 256,
    "batch_size": 16,
    "per_query_energy_j": 68.3,
    "modality": "text_batched",
    "model": "Phi-3-mini-4k",
    "params_B": 3.8,
    "run": 17,
    "hardware": "NVIDIA H100 80GB HBM3",
    "backend": "cuda"
  },
  {
    "total_energy_j": 1120.92,
    "avg_power_w": 205.38,
    "max_power_w": 235.28,
    "duration_sec": 5.46,
    "samples": 110,
    "generation_time_sec": 5.47,
    "max_tokens": 256,
    "batch_size": 16,
    "per_query_energy_j": 70.06,
    "modality": "text_batched",
    "model": "Phi-3-mini-4k",
    "params_B": 3.8,
    "run": 18,
    "hardware": "NVIDIA H100 80GB HBM3",
    "backend": "cuda"
  },
  {
    "total_energy_j": 1089.49,
    "avg_power_w": 205.2,
    "max_power_w": 233.26,
    "duration_sec": 5.32,
    "samples": 107,
    "generation_time_sec": 5.34,
    "max_tokens": 256,
    "batch_size": 16,
    "per_query_energy_j": 68.09,
    "modality": "text_batched",
    "model": "Phi-3-mini-4k",
    "params_B": 3.8,
    "run": 19,
    "hardware": "NVIDIA H100 80GB HBM3",
    "backend": "cuda"
  },
  {
    "total_energy_j": 1094.21,
    "avg_power_w": 206.22,
    "max_power_w": 234.02,
    "duration_sec": 5.31,
    "samples": 107,
    "generation_time_sec": 5.32,
    "max_tokens": 256,
    "batch_size": 16,
    "per_query_energy_j": 68.39,
    "modality": "text_batched",
    "model": "Phi-3-mini-4k",
    "params_B": 3.8,
    "run": 20,
    "hardware": "NVIDIA H100 80GB HBM3",
    "backend": "cuda"
  },
  {
    "total_energy_j": 1094.92,
    "avg_power_w": 206.33,
    "max_power_w": 232.87,
    "duration_sec": 5.31,
    "samples": 107,
    "generation_time_sec": 5.34,
    "max_tokens": 256,
    "batch_size": 16,
    "per_query_energy_j": 68.43,
    "modality": "text_batched",
    "model": "Phi-3-mini-4k",
    "params_B": 3.8,
    "run": 21,
    "hardware": "NVIDIA H100 80GB HBM3",
    "backend": "cuda"
  },
  {
    "total_energy_j": 1104.18,
    "avg_power_w": 204.22,
    "max_power_w": 232.0,
    "duration_sec": 5.41,
    "samples": 109,
    "generation_time_sec": 5.45,
    "max_tokens": 256,
    "batch_size": 16,
    "per_query_energy_j": 69.01,
    "modality": "text_batched",
    "model": "Phi-3-mini-4k",
    "params_B": 3.8,
    "run": 22,
    "hardware": "NVIDIA H100 80GB HBM3",
    "backend": "cuda"
  },
  {
    "total_energy_j": 1101.3,
    "avg_power_w": 205.6,
    "max_power_w": 231.12,
    "duration_sec": 5.36,
    "samples": 108,
    "generation_time_sec": 5.37,
    "max_tokens": 256,
    "batch_size": 16,
    "per_query_energy_j": 68.83,
    "modality": "text_batched",
    "model": "Phi-3-mini-4k",
    "params_B": 3.8,
    "run": 23,
    "hardware": "NVIDIA H100 80GB HBM3",
    "backend": "cuda"
  },
  {
    "total_energy_j": 1104.37,
    "avg_power_w": 204.12,
    "max_power_w": 231.9,
    "duration_sec": 5.42,
    "samples": 109,
    "generation_time_sec": 5.44,
    "max_tokens": 256,
    "batch_size": 16,
    "per_query_energy_j": 69.02,
    "modality": "text_batched",
    "model": "Phi-3-mini-4k",
    "params_B": 3.8,
    "run": 24,
    "hardware": "NVIDIA H100 80GB HBM3",
    "backend": "cuda"
  },
  {
    "total_energy_j": 1086.02,
    "avg_power_w": 206.57,
    "max_power_w": 230.27,
    "duration_sec": 5.26,
    "samples": 106,
    "generation_time_sec": 5.31,
    "max_tokens": 256,
    "batch_size": 16,
    "per_query_energy_j": 67.88,
    "modality": "text_batched",
    "model": "Phi-3-mini-4k",
    "params_B": 3.8,
    "run": 25,
    "hardware": "NVIDIA H100 80GB HBM3",
    "backend": "cuda"
  },
  {
    "total_energy_j": 1103.01,
    "avg_power_w": 205.84,
    "max_power_w": 231.6,
    "duration_sec": 5.36,
    "samples": 108,
    "generation_time_sec": 5.41,
    "max_tokens": 256,
    "batch_size": 16,
    "per_query_energy_j": 68.94,
    "modality": "text_batched",
    "model": "Phi-3-mini-4k",
    "params_B": 3.8,
    "run": 26,
    "hardware": "NVIDIA H100 80GB HBM3",
    "backend": "cuda"
  },
  {
    "total_energy_j": 1109.13,
    "avg_power_w": 205.17,
    "max_power_w": 231.63,
    "duration_sec": 5.41,
    "samples": 109,
    "generation_time_sec": 5.43,
    "max_tokens": 256,
    "batch_size": 16,
    "per_query_energy_j": 69.32,
    "modality": "text_batched",
    "model": "Phi-3-mini-4k",
    "params_B": 3.8,
    "run": 27,
    "hardware": "NVIDIA H100 80GB HBM3",
    "backend": "cuda"
  },
  {
    "total_energy_j": 1102.75,
    "avg_power_w": 205.84,
    "max_power_w": 230.41,
    "duration_sec": 5.36,
    "samples": 108,
    "generation_time_sec": 5.38,
    "max_tokens": 256,
    "batch_size": 16,
    "per_query_energy_j": 68.92,
    "modality": "text_batched",
    "model": "Phi-3-mini-4k",
    "params_B": 3.8,
    "run": 28,
    "hardware": "NVIDIA H100 80GB HBM3",
    "backend": "cuda"
  },
  {
    "total_energy_j": 1102.82,
    "avg_power_w": 203.93,
    "max_power_w": 231.49,
    "duration_sec": 5.41,
    "samples": 109,
    "generation_time_sec": 5.46,
    "max_tokens": 256,
    "batch_size": 16,
    "per_query_energy_j": 68.93,
    "modality": "text_batched",
    "model": "Phi-3-mini-4k",
    "params_B": 3.8,
    "run": 29,
    "hardware": "NVIDIA H100 80GB HBM3",
    "backend": "cuda"
  },
  {
    "total_energy_j": 1096.24,
    "avg_power_w": 206.6,
    "max_power_w": 233.5,
    "duration_sec": 5.31,
    "samples": 107,
    "generation_time_sec": 5.35,
    "max_tokens": 256,
    "batch_size": 16,
    "per_query_energy_j": 68.52,
    "modality": "text_batched",
    "model": "Phi-3-mini-4k",
    "params_B": 3.8,
    "run": 30,
    "hardware": "NVIDIA H100 80GB HBM3",
    "backend": "cuda"
  }
]