[
  {
    "total_energy_j": 41.85,
    "avg_power_w": 15.36,
    "max_power_w": 19.45,
    "duration_sec": 2.51,
    "samples": 5,
    "generation_time_sec": 2.73,
    "resolution": "256x256",
    "steps": 20,
    "modality": "image",
    "model": "SD-v1-5",
    "params_B": 0.9,
    "run": 1
  },
  {
    "total_energy_j": 40.2,
    "avg_power_w": 15.38,
    "max_power_w": 19.3,
    "duration_sec": 2.44,
    "samples": 5,
    "generation_time_sec": 2.72,
    "resolution": "256x256",
    "steps": 20,
    "modality": "image",
    "model": "SD-v1-5",
    "params_B": 0.9,
    "run": 2
  },
  {
    "total_energy_j": 42.19,
    "avg_power_w": 14.88,
    "max_power_w": 19.41,
    "duration_sec": 2.59,
    "samples": 5,
    "generation_time_sec": 2.72,
    "resolution": "256x256",
    "steps": 20,
    "modality": "image",
    "model": "SD-v1-5",
    "params_B": 0.9,
    "run": 3
  },
  {
    "total_energy_j": 40.76,
    "avg_power_w": 14.14,
    "max_power_w": 18.32,
    "duration_sec": 2.62,
    "samples": 5,
    "generation_time_sec": 2.7,
    "resolution": "256x256",
    "steps": 20,
    "modality": "image",
    "model": "SD-v1-5",
    "params_B": 0.9,
    "run": 4
  },
  {
    "total_energy_j": 41.25,
    "avg_power_w": 14.29,
    "max_power_w": 17.97,
    "duration_sec": 2.64,
    "samples": 5,
    "generation_time_sec": 2.72,
    "resolution": "256x256",
    "steps": 20,
    "modality": "image",
    "model": "SD-v1-5",
    "params_B": 0.9,
    "run": 5
  },
  {
    "total_energy_j": 41.69,
    "avg_power_w": 15.7,
    "max_power_w": 19.31,
    "duration_sec": 2.46,
    "samples": 5,
    "generation_time_sec": 2.73,
    "resolution": "256x256",
    "steps": 20,
    "modality": "image",
    "model": "SD-v1-5",
    "params_B": 0.9,
    "run": 6
  },
  {
    "total_energy_j": 40.95,
    "avg_power_w": 15.11,
    "max_power_w": 19.07,
    "duration_sec": 2.53,
    "samples": 5,
    "generation_time_sec": 2.74,
    "resolution": "256x256",
    "steps": 20,
    "modality": "image",
    "model": "SD-v1-5",
    "params_B": 0.9,
    "run": 7
  },
  {
    "total_energy_j": 38.9,
    "avg_power_w": 14.95,
    "max_power_w": 17.78,
    "duration_sec": 2.45,
    "samples": 5,
    "generation_time_sec": 2.71,
    "resolution": "256x256",
    "steps": 20,
    "modality": "image",
    "model": "SD-v1-5",
    "params_B": 0.9,
    "run": 8
  },
  {
    "total_energy_j": 40.45,
    "avg_power_w": 15.08,
    "max_power_w": 19.64,
    "duration_sec": 2.5,
    "samples": 5,
    "generation_time_sec": 2.7,
    "resolution": "256x256",
    "steps": 20,
    "modality": "image",
    "model": "SD-v1-5",
    "params_B": 0.9,
    "run": 9
  },
  {
    "total_energy_j": 43.93,
    "avg_power_w": 14.94,
    "max_power_w": 20.16,
    "duration_sec": 2.65,
    "samples": 5,
    "generation_time_sec": 2.7,
    "resolution": "256x256",
    "steps": 20,
    "modality": "image",
    "model": "SD-v1-5",
    "params_B": 0.9,
    "run": 10
  },
  {
    "total_energy_j": 43.29,
    "avg_power_w": 14.59,
    "max_power_w": 19.35,
    "duration_sec": 2.66,
    "samples": 5,
    "generation_time_sec": 2.7,
    "resolution": "256x256",
    "steps": 20,
    "modality": "image",
    "model": "SD-v1-5",
    "params_B": 0.9,
    "run": 11
  },
  {
    "total_energy_j": 40.3,
    "avg_power_w": 15.09,
    "max_power_w": 19.3,
    "duration_sec": 2.51,
    "samples": 5,
    "generation_time_sec": 2.72,
    "resolution": "256x256",
    "steps": 20,
    "modality": "image",
    "model": "SD-v1-5",
    "params_B": 0.9,
    "run": 12
  },
  {
    "total_energy_j": 40.54,
    "avg_power_w": 13.75,
    "max_power_w": 18.39,
    "duration_sec": 2.66,
    "samples": 5,
    "generation_time_sec": 2.72,
    "resolution": "256x256",
    "steps": 20,
    "modality": "image",
    "model": "SD-v1-5",
    "params_B": 0.9,
    "run": 13
  },
  {
    "total_energy_j": 42.14,
    "avg_power_w": 15.1,
    "max_power_w": 19.17,
    "duration_sec": 2.58,
    "samples": 5,
    "generation_time_sec": 2.73,
    "resolution": "256x256",
    "steps": 20,
    "modality": "image",
    "model": "SD-v1-5",
    "params_B": 0.9,
    "run": 14
  },
  {
    "total_energy_j": 40.84,
    "avg_power_w": 13.93,
    "max_power_w": 18.22,
    "duration_sec": 2.63,
    "samples": 5,
    "generation_time_sec": 2.69,
    "resolution": "256x256",
    "steps": 20,
    "modality": "image",
    "model": "SD-v1-5",
    "params_B": 0.9,
    "run": 15
  },
  {
    "total_energy_j": 40.0,
    "avg_power_w": 14.52,
    "max_power_w": 18.13,
    "duration_sec": 2.55,
    "samples": 5,
    "generation_time_sec": 2.71,
    "resolution": "256x256",
    "steps": 20,
    "modality": "image",
    "model": "SD-v1-5",
    "params_B": 0.9,
    "run": 16
  },
  {
    "total_energy_j": 39.22,
    "avg_power_w": 14.87,
    "max_power_w": 17.78,
    "duration_sec": 2.48,
    "samples": 5,
    "generation_time_sec": 2.72,
    "resolution": "256x256",
    "steps": 20,
    "modality": "image",
    "model": "SD-v1-5",
    "params_B": 0.9,
    "run": 17
  },
  {
    "total_energy_j": 40.94,
    "avg_power_w": 14.0,
    "max_power_w": 18.09,
    "duration_sec": 2.66,
    "samples": 5,
    "generation_time_sec": 2.72,
    "resolution": "256x256",
    "steps": 20,
    "modality": "image",
    "model": "SD-v1-5",
    "params_B": 0.9,
    "run": 18
  },
  {
    "total_energy_j": 40.54,
    "avg_power_w": 14.31,
    "max_power_w": 17.77,
    "duration_sec": 2.62,
    "samples": 5,
    "generation_time_sec": 2.74,
    "resolution": "256x256",
    "steps": 20,
    "modality": "image",
    "model": "SD-v1-5",
    "params_B": 0.9,
    "run": 19
  },
  {
    "total_energy_j": 44.59,
    "avg_power_w": 15.61,
    "max_power_w": 19.73,
    "duration_sec": 2.6,
    "samples": 5,
    "generation_time_sec": 2.71,
    "resolution": "256x256",
    "steps": 20,
    "modality": "image",
    "model": "SD-v1-5",
    "params_B": 0.9,
    "run": 20
  },
  {
    "total_energy_j": 41.84,
    "avg_power_w": 15.17,
    "max_power_w": 19.61,
    "duration_sec": 2.54,
    "samples": 5,
    "generation_time_sec": 2.7,
    "resolution": "256x256",
    "steps": 20,
    "modality": "image",
    "model": "SD-v1-5",
    "params_B": 0.9,
    "run": 21
  },
  {
    "total_energy_j": 42.12,
    "avg_power_w": 14.34,
    "max_power_w": 18.62,
    "duration_sec": 2.66,
    "samples": 5,
    "generation_time_sec": 2.7,
    "resolution": "256x256",
    "steps": 20,
    "modality": "image",
    "model": "SD-v1-5",
    "params_B": 0.9,
    "run": 22
  },
  {
    "total_energy_j": 40.88,
    "avg_power_w": 13.95,
    "max_power_w": 18.08,
    "duration_sec": 2.65,
    "samples": 5,
    "generation_time_sec": 2.69,
    "resolution": "256x256",
    "steps": 20,
    "modality": "image",
    "model": "SD-v1-5",
    "params_B": 0.9,
    "run": 23
  },
  {
    "total_energy_j": 43.38,
    "avg_power_w": 14.93,
    "max_power_w": 19.92,
    "duration_sec": 2.63,
    "samples": 5,
    "generation_time_sec": 2.72,
    "resolution": "256x256",
    "steps": 20,
    "modality": "image",
    "model": "SD-v1-5",
    "params_B": 0.9,
    "run": 24
  },
  {
    "total_energy_j": 39.94,
    "avg_power_w": 14.42,
    "max_power_w": 18.42,
    "duration_sec": 2.56,
    "samples": 5,
    "generation_time_sec": 2.72,
    "resolution": "256x256",
    "steps": 20,
    "modality": "image",
    "model": "SD-v1-5",
    "params_B": 0.9,
    "run": 25
  },
  {
    "total_energy_j": 42.01,
    "avg_power_w": 14.35,
    "max_power_w": 18.53,
    "duration_sec": 2.66,
    "samples": 5,
    "generation_time_sec": 2.7,
    "resolution": "256x256",
    "steps": 20,
    "modality": "image",
    "model": "SD-v1-5",
    "params_B": 0.9,
    "run": 26
  },
  {
    "total_energy_j": 41.26,
    "avg_power_w": 15.29,
    "max_power_w": 19.14,
    "duration_sec": 2.49,
    "samples": 5,
    "generation_time_sec": 2.7,
    "resolution": "256x256",
    "steps": 20,
    "modality": "image",
    "model": "SD-v1-5",
    "params_B": 0.9,
    "run": 27
  },
  {
    "total_energy_j": 40.3,
    "avg_power_w": 13.93,
    "max_power_w": 18.03,
    "duration_sec": 2.62,
    "samples": 5,
    "generation_time_sec": 2.71,
    "resolution": "256x256",
    "steps": 20,
    "modality": "image",
    "model": "SD-v1-5",
    "params_B": 0.9,
    "run": 28
  },
  {
    "total_energy_j": 40.04,
    "avg_power_w": 14.93,
    "max_power_w": 18.13,
    "duration_sec": 2.48,
    "samples": 5,
    "generation_time_sec": 2.71,
    "resolution": "256x256",
    "steps": 20,
    "modality": "image",
    "model": "SD-v1-5",
    "params_B": 0.9,
    "run": 29
  },
  {
    "total_energy_j": 40.66,
    "avg_power_w": 14.47,
    "max_power_w": 18.07,
    "duration_sec": 2.59,
    "samples": 5,
    "generation_time_sec": 2.7,
    "resolution": "256x256",
    "steps": 20,
    "modality": "image",
    "model": "SD-v1-5",
    "params_B": 0.9,
    "run": 30
  },
  {
    "total_energy_j": 63.03,
    "avg_power_w": 16.27,
    "max_power_w": 19.05,
    "duration_sec": 3.64,
    "samples": 7,
    "generation_time_sec": 3.9,
    "resolution": "256x256",
    "steps": 30,
    "modality": "image",
    "model": "SD-v1-5",
    "params_B": 0.9,
    "run": 1
  },
  {
    "total_energy_j": 62.55,
    "avg_power_w": 16.23,
    "max_power_w": 18.93,
    "duration_sec": 3.66,
    "samples": 7,
    "generation_time_sec": 3.88,
    "resolution": "256x256",
    "steps": 30,
    "modality": "image",
    "model": "SD-v1-5",
    "params_B": 0.9,
    "run": 2
  },
  {
    "total_energy_j": 61.23,
    "avg_power_w": 16.17,
    "max_power_w": 18.64,
    "duration_sec": 3.58,
    "samples": 7,
    "generation_time_sec": 3.9,
    "resolution": "256x256",
    "steps": 30,
    "modality": "image",
    "model": "SD-v1-5",
    "params_B": 0.9,
    "run": 3
  },
  {
    "total_energy_j": 65.13,
    "avg_power_w": 14.37,
    "max_power_w": 18.32,
    "duration_sec": 4.13,
    "samples": 8,
    "generation_time_sec": 3.87,
    "resolution": "256x256",
    "steps": 30,
    "modality": "image",
    "model": "SD-v1-5",
    "params_B": 0.9,
    "run": 4
  },
  {
    "total_energy_j": 60.68,
    "avg_power_w": 15.6,
    "max_power_w": 18.11,
    "duration_sec": 3.7,
    "samples": 7,
    "generation_time_sec": 3.91,
    "resolution": "256x256",
    "steps": 30,
    "modality": "image",
    "model": "SD-v1-5",
    "params_B": 0.9,
    "run": 5
  },
  {
    "total_energy_j": 55.93,
    "avg_power_w": 16.97,
    "max_power_w": 19.1,
    "duration_sec": 3.2,
    "samples": 6,
    "generation_time_sec": 3.85,
    "resolution": "256x256",
    "steps": 30,
    "modality": "image",
    "model": "SD-v1-5",
    "params_B": 0.9,
    "run": 6
  },
  {
    "total_energy_j": 61.19,
    "avg_power_w": 15.68,
    "max_power_w": 18.11,
    "duration_sec": 3.71,
    "samples": 7,
    "generation_time_sec": 3.88,
    "resolution": "256x256",
    "steps": 30,
    "modality": "image",
    "model": "SD-v1-5",
    "params_B": 0.9,
    "run": 7
  },
  {
    "total_energy_j": 61.75,
    "avg_power_w": 15.55,
    "max_power_w": 18.28,
    "duration_sec": 3.74,
    "samples": 7,
    "generation_time_sec": 3.87,
    "resolution": "256x256",
    "steps": 30,
    "modality": "image",
    "model": "SD-v1-5",
    "params_B": 0.9,
    "run": 8
  },
  {
    "total_energy_j": 61.18,
    "avg_power_w": 15.67,
    "max_power_w": 18.81,
    "duration_sec": 3.67,
    "samples": 7,
    "generation_time_sec": 3.91,
    "resolution": "256x256",
    "steps": 30,
    "modality": "image",
    "model": "SD-v1-5",
    "params_B": 0.9,
    "run": 9
  },
  {
    "total_energy_j": 66.1,
    "avg_power_w": 16.47,
    "max_power_w": 20.22,
    "duration_sec": 3.74,
    "samples": 7,
    "generation_time_sec": 3.87,
    "resolution": "256x256",
    "steps": 30,
    "modality": "image",
    "model": "SD-v1-5",
    "params_B": 0.9,
    "run": 10
  },
  {
    "total_energy_j": 58.66,
    "avg_power_w": 17.18,
    "max_power_w": 18.91,
    "duration_sec": 3.32,
    "samples": 6,
    "generation_time_sec": 3.86,
    "resolution": "256x256",
    "steps": 30,
    "modality": "image",
    "model": "SD-v1-5",
    "params_B": 0.9,
    "run": 11
  },
  {
    "total_energy_j": 62.49,
    "avg_power_w": 14.98,
    "max_power_w": 18.51,
    "duration_sec": 3.86,
    "samples": 7,
    "generation_time_sec": 3.88,
    "resolution": "256x256",
    "steps": 30,
    "modality": "image",
    "model": "SD-v1-5",
    "params_B": 0.9,
    "run": 12
  },
  {
    "total_energy_j": 61.96,
    "avg_power_w": 14.91,
    "max_power_w": 18.28,
    "duration_sec": 3.84,
    "samples": 7,
    "generation_time_sec": 3.88,
    "resolution": "256x256",
    "steps": 30,
    "modality": "image",
    "model": "SD-v1-5",
    "params_B": 0.9,
    "run": 13
  },
  {
    "total_energy_j": 61.22,
    "avg_power_w": 15.16,
    "max_power_w": 18.41,
    "duration_sec": 3.77,
    "samples": 7,
    "generation_time_sec": 3.88,
    "resolution": "256x256",
    "steps": 30,
    "modality": "image",
    "model": "SD-v1-5",
    "params_B": 0.9,
    "run": 14
  },
  {
    "total_energy_j": 61.85,
    "avg_power_w": 14.83,
    "max_power_w": 18.3,
    "duration_sec": 3.82,
    "samples": 7,
    "generation_time_sec": 3.88,
    "resolution": "256x256",
    "steps": 30,
    "modality": "image",
    "model": "SD-v1-5",
    "params_B": 0.9,
    "run": 15
  },
  {
    "total_energy_j": 66.39,
    "avg_power_w": 15.13,
    "max_power_w": 20.26,
    "duration_sec": 3.98,
    "samples": 7,
    "generation_time_sec": 3.88,
    "resolution": "256x256",
    "steps": 30,
    "modality": "image",
    "model": "SD-v1-5",
    "params_B": 0.9,
    "run": 16
  },
  {
    "total_energy_j": 62.57,
    "avg_power_w": 15.09,
    "max_power_w": 18.12,
    "duration_sec": 3.84,
    "samples": 7,
    "generation_time_sec": 3.87,
    "resolution": "256x256",
    "steps": 30,
    "modality": "image",
    "model": "SD-v1-5",
    "params_B": 0.9,
    "run": 17
  },
  {
    "total_energy_j": 62.78,
    "avg_power_w": 14.81,
    "max_power_w": 18.05,
    "duration_sec": 3.89,
    "samples": 7,
    "generation_time_sec": 3.87,
    "resolution": "256x256",
    "steps": 30,
    "modality": "image",
    "model": "SD-v1-5",
    "params_B": 0.9,
    "run": 18
  },
  {
    "total_energy_j": 62.56,
    "avg_power_w": 16.46,
    "max_power_w": 19.05,
    "duration_sec": 3.59,
    "samples": 7,
    "generation_time_sec": 3.87,
    "resolution": "256x256",
    "steps": 30,
    "modality": "image",
    "model": "SD-v1-5",
    "params_B": 0.9,
    "run": 19
  },
  {
    "total_energy_j": 62.63,
    "avg_power_w": 15.27,
    "max_power_w": 18.61,
    "duration_sec": 3.8,
    "samples": 7,
    "generation_time_sec": 3.9,
    "resolution": "256x256",
    "steps": 30,
    "modality": "image",
    "model": "SD-v1-5",
    "params_B": 0.9,
    "run": 20
  },
  {
    "total_energy_j": 59.8,
    "avg_power_w": 15.99,
    "max_power_w": 18.23,
    "duration_sec": 3.59,
    "samples": 7,
    "generation_time_sec": 3.88,
    "resolution": "256x256",
    "steps": 30,
    "modality": "image",
    "model": "SD-v1-5",
    "params_B": 0.9,
    "run": 21
  },
  {
    "total_energy_j": 62.96,
    "avg_power_w": 15.56,
    "max_power_w": 18.89,
    "duration_sec": 3.75,
    "samples": 7,
    "generation_time_sec": 3.88,
    "resolution": "256x256",
    "steps": 30,
    "modality": "image",
    "model": "SD-v1-5",
    "params_B": 0.9,
    "run": 22
  },
  {
    "total_energy_j": 67.28,
    "avg_power_w": 15.46,
    "max_power_w": 20.21,
    "duration_sec": 3.96,
    "samples": 7,
    "generation_time_sec": 3.87,
    "resolution": "256x256",
    "steps": 30,
    "modality": "image",
    "model": "SD-v1-5",
    "params_B": 0.9,
    "run": 23
  },
  {
    "total_energy_j": 63.43,
    "avg_power_w": 15.56,
    "max_power_w": 18.95,
    "duration_sec": 3.8,
    "samples": 7,
    "generation_time_sec": 3.89,
    "resolution": "256x256",
    "steps": 30,
    "modality": "image",
    "model": "SD-v1-5",
    "params_B": 0.9,
    "run": 24
  },
  {
    "total_energy_j": 61.43,
    "avg_power_w": 16.1,
    "max_power_w": 18.83,
    "duration_sec": 3.62,
    "samples": 7,
    "generation_time_sec": 3.87,
    "resolution": "256x256",
    "steps": 30,
    "modality": "image",
    "model": "SD-v1-5",
    "params_B": 0.9,
    "run": 25
  },
  {
    "total_energy_j": 61.89,
    "avg_power_w": 15.39,
    "max_power_w": 18.19,
    "duration_sec": 3.78,
    "samples": 7,
    "generation_time_sec": 3.87,
    "resolution": "256x256",
    "steps": 30,
    "modality": "image",
    "model": "SD-v1-5",
    "params_B": 0.9,
    "run": 26
  },
  {
    "total_energy_j": 63.26,
    "avg_power_w": 15.6,
    "max_power_w": 19.4,
    "duration_sec": 3.8,
    "samples": 7,
    "generation_time_sec": 3.87,
    "resolution": "256x256",
    "steps": 30,
    "modality": "image",
    "model": "SD-v1-5",
    "params_B": 0.9,
    "run": 27
  },
  {
    "total_energy_j": 62.97,
    "avg_power_w": 14.77,
    "max_power_w": 18.69,
    "duration_sec": 3.85,
    "samples": 7,
    "generation_time_sec": 3.86,
    "resolution": "256x256",
    "steps": 30,
    "modality": "image",
    "model": "SD-v1-5",
    "params_B": 0.9,
    "run": 28
  },
  {
    "total_energy_j": 63.81,
    "avg_power_w": 14.64,
    "max_power_w": 18.31,
    "duration_sec": 3.98,
    "samples": 7,
    "generation_time_sec": 3.87,
    "resolution": "256x256",
    "steps": 30,
    "modality": "image",
    "model": "SD-v1-5",
    "params_B": 0.9,
    "run": 29
  },
  {
    "total_energy_j": 65.41,
    "avg_power_w": 14.99,
    "max_power_w": 18.7,
    "duration_sec": 3.99,
    "samples": 7,
    "generation_time_sec": 3.87,
    "resolution": "256x256",
    "steps": 30,
    "modality": "image",
    "model": "SD-v1-5",
    "params_B": 0.9,
    "run": 30
  },
  {
    "total_energy_j": 137.23,
    "avg_power_w": 15.49,
    "max_power_w": 21.56,
    "duration_sec": 8.44,
    "samples": 14,
    "generation_time_sec": 8.81,
    "resolution": "384x384",
    "steps": 20,
    "modality": "image",
    "model": "SD-v1-5",
    "params_B": 0.9,
    "run": 1
  },
  {
    "total_energy_j": 123.76,
    "avg_power_w": 20.39,
    "max_power_w": 21.79,
    "duration_sec": 5.96,
    "samples": 10,
    "generation_time_sec": 6.4,
    "resolution": "384x384",
    "steps": 20,
    "modality": "image",
    "model": "SD-v1-5",
    "params_B": 0.9,
    "run": 2
  },
  {
    "total_energy_j": 113.05,
    "avg_power_w": 17.67,
    "max_power_w": 20.08,
    "duration_sec": 6.26,
    "samples": 11,
    "generation_time_sec": 6.78,
    "resolution": "384x384",
    "steps": 20,
    "modality": "image",
    "model": "SD-v1-5",
    "params_B": 0.9,
    "run": 3
  },
  {
    "total_energy_j": 122.35,
    "avg_power_w": 16.87,
    "max_power_w": 19.51,
    "duration_sec": 6.91,
    "samples": 12,
    "generation_time_sec": 6.79,
    "resolution": "384x384",
    "steps": 20,
    "modality": "image",
    "model": "SD-v1-5",
    "params_B": 0.9,
    "run": 4
  },
  {
    "total_energy_j": 124.3,
    "avg_power_w": 16.78,
    "max_power_w": 20.18,
    "duration_sec": 6.98,
    "samples": 12,
    "generation_time_sec": 6.77,
    "resolution": "384x384",
    "steps": 20,
    "modality": "image",
    "model": "SD-v1-5",
    "params_B": 0.9,
    "run": 5
  },
  {
    "total_energy_j": 120.69,
    "avg_power_w": 16.9,
    "max_power_w": 19.83,
    "duration_sec": 6.84,
    "samples": 12,
    "generation_time_sec": 6.77,
    "resolution": "384x384",
    "steps": 20,
    "modality": "image",
    "model": "SD-v1-5",
    "params_B": 0.9,
    "run": 6
  },
  {
    "total_energy_j": 119.01,
    "avg_power_w": 16.99,
    "max_power_w": 19.49,
    "duration_sec": 6.7,
    "samples": 12,
    "generation_time_sec": 6.77,
    "resolution": "384x384",
    "steps": 20,
    "modality": "image",
    "model": "SD-v1-5",
    "params_B": 0.9,
    "run": 7
  },
  {
    "total_energy_j": 119.34,
    "avg_power_w": 16.63,
    "max_power_w": 19.68,
    "duration_sec": 6.79,
    "samples": 12,
    "generation_time_sec": 6.76,
    "resolution": "384x384",
    "steps": 20,
    "modality": "image",
    "model": "SD-v1-5",
    "params_B": 0.9,
    "run": 8
  },
  {
    "total_energy_j": 115.42,
    "avg_power_w": 17.46,
    "max_power_w": 20.88,
    "duration_sec": 6.44,
    "samples": 11,
    "generation_time_sec": 6.79,
    "resolution": "384x384",
    "steps": 20,
    "modality": "image",
    "model": "SD-v1-5",
    "params_B": 0.9,
    "run": 9
  },
  {
    "total_energy_j": 123.05,
    "avg_power_w": 16.56,
    "max_power_w": 20.14,
    "duration_sec": 7.03,
    "samples": 12,
    "generation_time_sec": 6.79,
    "resolution": "384x384",
    "steps": 20,
    "modality": "image",
    "model": "SD-v1-5",
    "params_B": 0.9,
    "run": 10
  },
  {
    "total_energy_j": 120.68,
    "avg_power_w": 17.64,
    "max_power_w": 20.19,
    "duration_sec": 6.61,
    "samples": 12,
    "generation_time_sec": 6.79,
    "resolution": "384x384",
    "steps": 20,
    "modality": "image",
    "model": "SD-v1-5",
    "params_B": 0.9,
    "run": 11
  },
  {
    "total_energy_j": 115.4,
    "avg_power_w": 17.37,
    "max_power_w": 19.65,
    "duration_sec": 6.43,
    "samples": 11,
    "generation_time_sec": 6.79,
    "resolution": "384x384",
    "steps": 20,
    "modality": "image",
    "model": "SD-v1-5",
    "params_B": 0.9,
    "run": 12
  },
  {
    "total_energy_j": 122.22,
    "avg_power_w": 17.08,
    "max_power_w": 20.3,
    "duration_sec": 6.87,
    "samples": 12,
    "generation_time_sec": 6.8,
    "resolution": "384x384",
    "steps": 20,
    "modality": "image",
    "model": "SD-v1-5",
    "params_B": 0.9,
    "run": 13
  },
  {
    "total_energy_j": 120.68,
    "avg_power_w": 17.43,
    "max_power_w": 19.67,
    "duration_sec": 6.67,
    "samples": 12,
    "generation_time_sec": 6.82,
    "resolution": "384x384",
    "steps": 20,
    "modality": "image",
    "model": "SD-v1-5",
    "params_B": 0.9,
    "run": 14
  },
  {
    "total_energy_j": 124.94,
    "avg_power_w": 16.53,
    "max_power_w": 21.32,
    "duration_sec": 7.11,
    "samples": 12,
    "generation_time_sec": 6.78,
    "resolution": "384x384",
    "steps": 20,
    "modality": "image",
    "model": "SD-v1-5",
    "params_B": 0.9,
    "run": 15
  },
  {
    "total_energy_j": 118.48,
    "avg_power_w": 17.86,
    "max_power_w": 19.91,
    "duration_sec": 6.47,
    "samples": 11,
    "generation_time_sec": 6.78,
    "resolution": "384x384",
    "steps": 20,
    "modality": "image",
    "model": "SD-v1-5",
    "params_B": 0.9,
    "run": 16
  },
  {
    "total_energy_j": 119.12,
    "avg_power_w": 17.62,
    "max_power_w": 19.63,
    "duration_sec": 6.58,
    "samples": 12,
    "generation_time_sec": 6.79,
    "resolution": "384x384",
    "steps": 20,
    "modality": "image",
    "model": "SD-v1-5",
    "params_B": 0.9,
    "run": 17
  },
  {
    "total_energy_j": 117.98,
    "avg_power_w": 17.6,
    "max_power_w": 19.83,
    "duration_sec": 6.5,
    "samples": 12,
    "generation_time_sec": 6.78,
    "resolution": "384x384",
    "steps": 20,
    "modality": "image",
    "model": "SD-v1-5",
    "params_B": 0.9,
    "run": 18
  },
  {
    "total_energy_j": 122.78,
    "avg_power_w": 16.87,
    "max_power_w": 20.54,
    "duration_sec": 6.92,
    "samples": 12,
    "generation_time_sec": 6.79,
    "resolution": "384x384",
    "steps": 20,
    "modality": "image",
    "model": "SD-v1-5",
    "params_B": 0.9,
    "run": 19
  },
  {
    "total_energy_j": 118.82,
    "avg_power_w": 17.15,
    "max_power_w": 19.68,
    "duration_sec": 6.67,
    "samples": 12,
    "generation_time_sec": 6.8,
    "resolution": "384x384",
    "steps": 20,
    "modality": "image",
    "model": "SD-v1-5",
    "params_B": 0.9,
    "run": 20
  },
  {
    "total_energy_j": 118.4,
    "avg_power_w": 17.46,
    "max_power_w": 20.15,
    "duration_sec": 6.6,
    "samples": 12,
    "generation_time_sec": 6.8,
    "resolution": "384x384",
    "steps": 20,
    "modality": "image",
    "model": "SD-v1-5",
    "params_B": 0.9,
    "run": 21
  },
  {
    "total_energy_j": 123.71,
    "avg_power_w": 16.83,
    "max_power_w": 21.03,
    "duration_sec": 6.89,
    "samples": 12,
    "generation_time_sec": 6.8,
    "resolution": "384x384",
    "steps": 20,
    "modality": "image",
    "model": "SD-v1-5",
    "params_B": 0.9,
    "run": 22
  },
  {
    "total_energy_j": 119.55,
    "avg_power_w": 17.36,
    "max_power_w": 19.79,
    "duration_sec": 6.68,
    "samples": 12,
    "generation_time_sec": 6.8,
    "resolution": "384x384",
    "steps": 20,
    "modality": "image",
    "model": "SD-v1-5",
    "params_B": 0.9,
    "run": 23
  },
  {
    "total_energy_j": 121.69,
    "avg_power_w": 16.66,
    "max_power_w": 21.04,
    "duration_sec": 6.92,
    "samples": 12,
    "generation_time_sec": 6.76,
    "resolution": "384x384",
    "steps": 20,
    "modality": "image",
    "model": "SD-v1-5",
    "params_B": 0.9,
    "run": 24
  },
  {
    "total_energy_j": 119.41,
    "avg_power_w": 16.85,
    "max_power_w": 20.24,
    "duration_sec": 6.84,
    "samples": 12,
    "generation_time_sec": 6.93,
    "resolution": "384x384",
    "steps": 20,
    "modality": "image",
    "model": "SD-v1-5",
    "params_B": 0.9,
    "run": 25
  },
  {
    "total_energy_j": 117.18,
    "avg_power_w": 17.69,
    "max_power_w": 19.83,
    "duration_sec": 6.46,
    "samples": 11,
    "generation_time_sec": 6.81,
    "resolution": "384x384",
    "steps": 20,
    "modality": "image",
    "model": "SD-v1-5",
    "params_B": 0.9,
    "run": 26
  },
  {
    "total_energy_j": 118.45,
    "avg_power_w": 16.86,
    "max_power_w": 19.73,
    "duration_sec": 6.74,
    "samples": 12,
    "generation_time_sec": 6.82,
    "resolution": "384x384",
    "steps": 20,
    "modality": "image",
    "model": "SD-v1-5",
    "params_B": 0.9,
    "run": 27
  },
  {
    "total_energy_j": 115.17,
    "avg_power_w": 17.59,
    "max_power_w": 19.61,
    "duration_sec": 6.41,
    "samples": 11,
    "generation_time_sec": 6.76,
    "resolution": "384x384",
    "steps": 20,
    "modality": "image",
    "model": "SD-v1-5",
    "params_B": 0.9,
    "run": 28
  },
  {
    "total_energy_j": 115.47,
    "avg_power_w": 18.11,
    "max_power_w": 21.46,
    "duration_sec": 6.29,
    "samples": 11,
    "generation_time_sec": 6.74,
    "resolution": "384x384",
    "steps": 20,
    "modality": "image",
    "model": "SD-v1-5",
    "params_B": 0.9,
    "run": 29
  },
  {
    "total_energy_j": 119.03,
    "avg_power_w": 17.85,
    "max_power_w": 20.15,
    "duration_sec": 6.49,
    "samples": 11,
    "generation_time_sec": 6.79,
    "resolution": "384x384",
    "steps": 20,
    "modality": "image",
    "model": "SD-v1-5",
    "params_B": 0.9,
    "run": 30
  },
  {
    "total_energy_j": 175.52,
    "avg_power_w": 18.03,
    "max_power_w": 20.23,
    "duration_sec": 9.54,
    "samples": 16,
    "generation_time_sec": 9.83,
    "resolution": "384x384",
    "steps": 30,
    "modality": "image",
    "model": "SD-v1-5",
    "params_B": 0.9,
    "run": 1
  },
  {
    "total_energy_j": 194.85,
    "avg_power_w": 20.65,
    "max_power_w": 22.55,
    "duration_sec": 9.12,
    "samples": 15,
    "generation_time_sec": 9.29,
    "resolution": "384x384",
    "steps": 30,
    "modality": "image",
    "model": "SD-v1-5",
    "params_B": 0.9,
    "run": 2
  },
  {
    "total_energy_j": 176.98,
    "avg_power_w": 17.57,
    "max_power_w": 19.68,
    "duration_sec": 9.8,
    "samples": 17,
    "generation_time_sec": 9.86,
    "resolution": "384x384",
    "steps": 30,
    "modality": "image",
    "model": "SD-v1-5",
    "params_B": 0.9,
    "run": 3
  },
  {
    "total_energy_j": 174.39,
    "avg_power_w": 18.0,
    "max_power_w": 19.55,
    "duration_sec": 9.54,
    "samples": 16,
    "generation_time_sec": 9.83,
    "resolution": "384x384",
    "steps": 30,
    "modality": "image",
    "model": "SD-v1-5",
    "params_B": 0.9,
    "run": 4
  },
  {
    "total_energy_j": 181.99,
    "avg_power_w": 17.52,
    "max_power_w": 20.57,
    "duration_sec": 9.97,
    "samples": 17,
    "generation_time_sec": 9.83,
    "resolution": "384x384",
    "steps": 30,
    "modality": "image",
    "model": "SD-v1-5",
    "params_B": 0.9,
    "run": 5
  },
  {
    "total_energy_j": 180.03,
    "avg_power_w": 17.68,
    "max_power_w": 20.16,
    "duration_sec": 9.87,
    "samples": 17,
    "generation_time_sec": 9.82,
    "resolution": "384x384",
    "steps": 30,
    "modality": "image",
    "model": "SD-v1-5",
    "params_B": 0.9,
    "run": 6
  },
  {
    "total_energy_j": 176.62,
    "avg_power_w": 17.59,
    "max_power_w": 19.81,
    "duration_sec": 9.75,
    "samples": 16,
    "generation_time_sec": 9.82,
    "resolution": "384x384",
    "steps": 30,
    "modality": "image",
    "model": "SD-v1-5",
    "params_B": 0.9,
    "run": 7
  },
  {
    "total_energy_j": 179.07,
    "avg_power_w": 17.75,
    "max_power_w": 19.54,
    "duration_sec": 9.83,
    "samples": 17,
    "generation_time_sec": 9.87,
    "resolution": "384x384",
    "steps": 30,
    "modality": "image",
    "model": "SD-v1-5",
    "params_B": 0.9,
    "run": 8
  },
  {
    "total_energy_j": 178.18,
    "avg_power_w": 18.35,
    "max_power_w": 20.25,
    "duration_sec": 9.54,
    "samples": 16,
    "generation_time_sec": 9.82,
    "resolution": "384x384",
    "steps": 30,
    "modality": "image",
    "model": "SD-v1-5",
    "params_B": 0.9,
    "run": 9
  },
  {
    "total_energy_j": 177.16,
    "avg_power_w": 17.9,
    "max_power_w": 20.55,
    "duration_sec": 9.67,
    "samples": 17,
    "generation_time_sec": 9.82,
    "resolution": "384x384",
    "steps": 30,
    "modality": "image",
    "model": "SD-v1-5",
    "params_B": 0.9,
    "run": 10
  },
  {
    "total_energy_j": 177.79,
    "avg_power_w": 18.52,
    "max_power_w": 20.24,
    "duration_sec": 9.46,
    "samples": 16,
    "generation_time_sec": 9.81,
    "resolution": "384x384",
    "steps": 30,
    "modality": "image",
    "model": "SD-v1-5",
    "params_B": 0.9,
    "run": 11
  },
  {
    "total_energy_j": 181.7,
    "avg_power_w": 17.25,
    "max_power_w": 20.89,
    "duration_sec": 10.07,
    "samples": 17,
    "generation_time_sec": 9.82,
    "resolution": "384x384",
    "steps": 30,
    "modality": "image",
    "model": "SD-v1-5",
    "params_B": 0.9,
    "run": 12
  },
  {
    "total_energy_j": 177.65,
    "avg_power_w": 17.77,
    "max_power_w": 19.51,
    "duration_sec": 9.74,
    "samples": 16,
    "generation_time_sec": 9.82,
    "resolution": "384x384",
    "steps": 30,
    "modality": "image",
    "model": "SD-v1-5",
    "params_B": 0.9,
    "run": 13
  },
  {
    "total_energy_j": 178.76,
    "avg_power_w": 17.51,
    "max_power_w": 20.28,
    "duration_sec": 9.81,
    "samples": 17,
    "generation_time_sec": 9.79,
    "resolution": "384x384",
    "steps": 30,
    "modality": "image",
    "model": "SD-v1-5",
    "params_B": 0.9,
    "run": 14
  },
  {
    "total_energy_j": 173.89,
    "avg_power_w": 18.32,
    "max_power_w": 21.1,
    "duration_sec": 9.37,
    "samples": 16,
    "generation_time_sec": 9.81,
    "resolution": "384x384",
    "steps": 30,
    "modality": "image",
    "model": "SD-v1-5",
    "params_B": 0.9,
    "run": 15
  },
  {
    "total_energy_j": 178.2,
    "avg_power_w": 17.36,
    "max_power_w": 20.09,
    "duration_sec": 9.89,
    "samples": 17,
    "generation_time_sec": 9.85,
    "resolution": "384x384",
    "steps": 30,
    "modality": "image",
    "model": "SD-v1-5",
    "params_B": 0.9,
    "run": 16
  },
  {
    "total_energy_j": 179.78,
    "avg_power_w": 17.49,
    "max_power_w": 20.68,
    "duration_sec": 9.9,
    "samples": 17,
    "generation_time_sec": 9.79,
    "resolution": "384x384",
    "steps": 30,
    "modality": "image",
    "model": "SD-v1-5",
    "params_B": 0.9,
    "run": 17
  },
  {
    "total_energy_j": 179.53,
    "avg_power_w": 17.45,
    "max_power_w": 20.64,
    "duration_sec": 9.95,
    "samples": 17,
    "generation_time_sec": 9.83,
    "resolution": "384x384",
    "steps": 30,
    "modality": "image",
    "model": "SD-v1-5",
    "params_B": 0.9,
    "run": 18
  },
  {
    "total_energy_j": 174.01,
    "avg_power_w": 17.89,
    "max_power_w": 20.3,
    "duration_sec": 9.53,
    "samples": 16,
    "generation_time_sec": 9.79,
    "resolution": "384x384",
    "steps": 30,
    "modality": "image",
    "model": "SD-v1-5",
    "params_B": 0.9,
    "run": 19
  },
  {
    "total_energy_j": 178.81,
    "avg_power_w": 16.86,
    "max_power_w": 21.4,
    "duration_sec": 10.13,
    "samples": 17,
    "generation_time_sec": 9.84,
    "resolution": "384x384",
    "steps": 30,
    "modality": "image",
    "model": "SD-v1-5",
    "params_B": 0.9,
    "run": 20
  },
  {
    "total_energy_j": 180.03,
    "avg_power_w": 17.49,
    "max_power_w": 20.03,
    "duration_sec": 9.98,
    "samples": 17,
    "generation_time_sec": 9.91,
    "resolution": "384x384",
    "steps": 30,
    "modality": "image",
    "model": "SD-v1-5",
    "params_B": 0.9,
    "run": 21
  },
  {
    "total_energy_j": 175.88,
    "avg_power_w": 18.41,
    "max_power_w": 19.95,
    "duration_sec": 9.44,
    "samples": 16,
    "generation_time_sec": 9.83,
    "resolution": "384x384",
    "steps": 30,
    "modality": "image",
    "model": "SD-v1-5",
    "params_B": 0.9,
    "run": 22
  },
  {
    "total_energy_j": 176.51,
    "avg_power_w": 17.76,
    "max_power_w": 20.15,
    "duration_sec": 9.64,
    "samples": 17,
    "generation_time_sec": 9.8,
    "resolution": "384x384",
    "steps": 30,
    "modality": "image",
    "model": "SD-v1-5",
    "params_B": 0.9,
    "run": 23
  },
  {
    "total_energy_j": 174.41,
    "avg_power_w": 18.25,
    "max_power_w": 22.52,
    "duration_sec": 9.44,
    "samples": 16,
    "generation_time_sec": 9.83,
    "resolution": "384x384",
    "steps": 30,
    "modality": "image",
    "model": "SD-v1-5",
    "params_B": 0.9,
    "run": 24
  },
  {
    "total_energy_j": 174.92,
    "avg_power_w": 18.48,
    "max_power_w": 19.83,
    "duration_sec": 9.37,
    "samples": 16,
    "generation_time_sec": 9.79,
    "resolution": "384x384",
    "steps": 30,
    "modality": "image",
    "model": "SD-v1-5",
    "params_B": 0.9,
    "run": 25
  },
  {
    "total_energy_j": 194.54,
    "avg_power_w": 21.13,
    "max_power_w": 23.6,
    "duration_sec": 9.01,
    "samples": 15,
    "generation_time_sec": 9.3,
    "resolution": "384x384",
    "steps": 30,
    "modality": "image",
    "model": "SD-v1-5",
    "params_B": 0.9,
    "run": 26
  },
  {
    "total_energy_j": 181.8,
    "avg_power_w": 17.37,
    "max_power_w": 20.48,
    "duration_sec": 10.07,
    "samples": 17,
    "generation_time_sec": 9.9,
    "resolution": "384x384",
    "steps": 30,
    "modality": "image",
    "model": "SD-v1-5",
    "params_B": 0.9,
    "run": 27
  },
  {
    "total_energy_j": 174.61,
    "avg_power_w": 18.12,
    "max_power_w": 20.36,
    "duration_sec": 9.5,
    "samples": 16,
    "generation_time_sec": 9.82,
    "resolution": "384x384",
    "steps": 30,
    "modality": "image",
    "model": "SD-v1-5",
    "params_B": 0.9,
    "run": 28
  },
  {
    "total_energy_j": 175.82,
    "avg_power_w": 18.39,
    "max_power_w": 21.64,
    "duration_sec": 9.43,
    "samples": 16,
    "generation_time_sec": 9.83,
    "resolution": "384x384",
    "steps": 30,
    "modality": "image",
    "model": "SD-v1-5",
    "params_B": 0.9,
    "run": 29
  },
  {
    "total_energy_j": 175.62,
    "avg_power_w": 18.46,
    "max_power_w": 20.2,
    "duration_sec": 9.4,
    "samples": 16,
    "generation_time_sec": 9.78,
    "resolution": "384x384",
    "steps": 30,
    "modality": "image",
    "model": "SD-v1-5",
    "params_B": 0.9,
    "run": 30
  },
  {
    "total_energy_j": 274.2,
    "avg_power_w": 20.11,
    "max_power_w": 25.26,
    "duration_sec": 13.14,
    "samples": 21,
    "generation_time_sec": 13.12,
    "resolution": "512x512",
    "steps": 20,
    "modality": "image",
    "model": "SD-v1-5",
    "params_B": 0.9,
    "run": 1
  },
  {
    "total_energy_j": 266.5,
    "avg_power_w": 20.98,
    "max_power_w": 22.88,
    "duration_sec": 12.55,
    "samples": 21,
    "generation_time_sec": 13.04,
    "resolution": "512x512",
    "steps": 20,
    "modality": "image",
    "model": "SD-v1-5",
    "params_B": 0.9,
    "run": 2
  },
  {
    "total_energy_j": 271.33,
    "avg_power_w": 20.46,
    "max_power_w": 25.04,
    "duration_sec": 12.88,
    "samples": 21,
    "generation_time_sec": 13.05,
    "resolution": "512x512",
    "steps": 20,
    "modality": "image",
    "model": "SD-v1-5",
    "params_B": 0.9,
    "run": 3
  },
  {
    "total_energy_j": 272.31,
    "avg_power_w": 20.65,
    "max_power_w": 23.29,
    "duration_sec": 12.92,
    "samples": 21,
    "generation_time_sec": 13.05,
    "resolution": "512x512",
    "steps": 20,
    "modality": "image",
    "model": "SD-v1-5",
    "params_B": 0.9,
    "run": 4
  },
  {
    "total_energy_j": 273.39,
    "avg_power_w": 20.58,
    "max_power_w": 23.65,
    "duration_sec": 12.99,
    "samples": 21,
    "generation_time_sec": 13.07,
    "resolution": "512x512",
    "steps": 20,
    "modality": "image",
    "model": "SD-v1-5",
    "params_B": 0.9,
    "run": 5
  },
  {
    "total_energy_j": 273.14,
    "avg_power_w": 20.62,
    "max_power_w": 22.71,
    "duration_sec": 12.98,
    "samples": 21,
    "generation_time_sec": 13.07,
    "resolution": "512x512",
    "steps": 20,
    "modality": "image",
    "model": "SD-v1-5",
    "params_B": 0.9,
    "run": 6
  },
  {
    "total_energy_j": 269.46,
    "avg_power_w": 21.03,
    "max_power_w": 22.35,
    "duration_sec": 12.74,
    "samples": 21,
    "generation_time_sec": 13.07,
    "resolution": "512x512",
    "steps": 20,
    "modality": "image",
    "model": "SD-v1-5",
    "params_B": 0.9,
    "run": 7
  },
  {
    "total_energy_j": 270.57,
    "avg_power_w": 21.13,
    "max_power_w": 26.37,
    "duration_sec": 12.69,
    "samples": 21,
    "generation_time_sec": 13.06,
    "resolution": "512x512",
    "steps": 20,
    "modality": "image",
    "model": "SD-v1-5",
    "params_B": 0.9,
    "run": 8
  },
  {
    "total_energy_j": 274.94,
    "avg_power_w": 20.38,
    "max_power_w": 23.91,
    "duration_sec": 13.12,
    "samples": 21,
    "generation_time_sec": 13.07,
    "resolution": "512x512",
    "steps": 20,
    "modality": "image",
    "model": "SD-v1-5",
    "params_B": 0.9,
    "run": 9
  },
  {
    "total_energy_j": 275.1,
    "avg_power_w": 20.34,
    "max_power_w": 24.96,
    "duration_sec": 13.1,
    "samples": 22,
    "generation_time_sec": 13.07,
    "resolution": "512x512",
    "steps": 20,
    "modality": "image",
    "model": "SD-v1-5",
    "params_B": 0.9,
    "run": 10
  },
  {
    "total_energy_j": 270.73,
    "avg_power_w": 20.82,
    "max_power_w": 22.13,
    "duration_sec": 12.82,
    "samples": 21,
    "generation_time_sec": 13.07,
    "resolution": "512x512",
    "steps": 20,
    "modality": "image",
    "model": "SD-v1-5",
    "params_B": 0.9,
    "run": 11
  },
  {
    "total_energy_j": 267.37,
    "avg_power_w": 20.86,
    "max_power_w": 23.32,
    "duration_sec": 12.55,
    "samples": 21,
    "generation_time_sec": 13.05,
    "resolution": "512x512",
    "steps": 20,
    "modality": "image",
    "model": "SD-v1-5",
    "params_B": 0.9,
    "run": 12
  },
  {
    "total_energy_j": 271.53,
    "avg_power_w": 20.79,
    "max_power_w": 22.12,
    "duration_sec": 12.85,
    "samples": 21,
    "generation_time_sec": 13.06,
    "resolution": "512x512",
    "steps": 20,
    "modality": "image",
    "model": "SD-v1-5",
    "params_B": 0.9,
    "run": 13
  },
  {
    "total_energy_j": 273.12,
    "avg_power_w": 20.17,
    "max_power_w": 25.28,
    "duration_sec": 13.11,
    "samples": 21,
    "generation_time_sec": 13.07,
    "resolution": "512x512",
    "steps": 20,
    "modality": "image",
    "model": "SD-v1-5",
    "params_B": 0.9,
    "run": 14
  },
  {
    "total_energy_j": 275.18,
    "avg_power_w": 20.4,
    "max_power_w": 24.42,
    "duration_sec": 13.09,
    "samples": 22,
    "generation_time_sec": 13.05,
    "resolution": "512x512",
    "steps": 20,
    "modality": "image",
    "model": "SD-v1-5",
    "params_B": 0.9,
    "run": 15
  },
  {
    "total_energy_j": 271.67,
    "avg_power_w": 20.79,
    "max_power_w": 22.72,
    "duration_sec": 12.85,
    "samples": 22,
    "generation_time_sec": 13.06,
    "resolution": "512x512",
    "steps": 20,
    "modality": "image",
    "model": "SD-v1-5",
    "params_B": 0.9,
    "run": 16
  },
  {
    "total_energy_j": 270.19,
    "avg_power_w": 20.81,
    "max_power_w": 24.38,
    "duration_sec": 12.81,
    "samples": 21,
    "generation_time_sec": 13.05,
    "resolution": "512x512",
    "steps": 20,
    "modality": "image",
    "model": "SD-v1-5",
    "params_B": 0.9,
    "run": 17
  },
  {
    "total_energy_j": 271.51,
    "avg_power_w": 20.57,
    "max_power_w": 24.46,
    "duration_sec": 12.82,
    "samples": 22,
    "generation_time_sec": 13.04,
    "resolution": "512x512",
    "steps": 20,
    "modality": "image",
    "model": "SD-v1-5",
    "params_B": 0.9,
    "run": 18
  },
  {
    "total_energy_j": 270.78,
    "avg_power_w": 20.75,
    "max_power_w": 22.2,
    "duration_sec": 12.85,
    "samples": 21,
    "generation_time_sec": 13.06,
    "resolution": "512x512",
    "steps": 20,
    "modality": "image",
    "model": "SD-v1-5",
    "params_B": 0.9,
    "run": 19
  },
  {
    "total_energy_j": 265.09,
    "avg_power_w": 20.96,
    "max_power_w": 24.21,
    "duration_sec": 12.58,
    "samples": 20,
    "generation_time_sec": 13.08,
    "resolution": "512x512",
    "steps": 20,
    "modality": "image",
    "model": "SD-v1-5",
    "params_B": 0.9,
    "run": 20
  },
  {
    "total_energy_j": 274.45,
    "avg_power_w": 20.95,
    "max_power_w": 22.78,
    "duration_sec": 12.9,
    "samples": 21,
    "generation_time_sec": 13.08,
    "resolution": "512x512",
    "steps": 20,
    "modality": "image",
    "model": "SD-v1-5",
    "params_B": 0.9,
    "run": 21
  },
  {
    "total_energy_j": 274.76,
    "avg_power_w": 20.26,
    "max_power_w": 23.92,
    "duration_sec": 13.16,
    "samples": 21,
    "generation_time_sec": 13.06,
    "resolution": "512x512",
    "steps": 20,
    "modality": "image",
    "model": "SD-v1-5",
    "params_B": 0.9,
    "run": 22
  },
  {
    "total_energy_j": 265.62,
    "avg_power_w": 21.2,
    "max_power_w": 23.55,
    "duration_sec": 12.43,
    "samples": 21,
    "generation_time_sec": 13.05,
    "resolution": "512x512",
    "steps": 20,
    "modality": "image",
    "model": "SD-v1-5",
    "params_B": 0.9,
    "run": 23
  },
  {
    "total_energy_j": 268.93,
    "avg_power_w": 20.88,
    "max_power_w": 23.56,
    "duration_sec": 12.72,
    "samples": 21,
    "generation_time_sec": 13.06,
    "resolution": "512x512",
    "steps": 20,
    "modality": "image",
    "model": "SD-v1-5",
    "params_B": 0.9,
    "run": 24
  },
  {
    "total_energy_j": 268.52,
    "avg_power_w": 20.89,
    "max_power_w": 22.47,
    "duration_sec": 12.75,
    "samples": 21,
    "generation_time_sec": 13.07,
    "resolution": "512x512",
    "steps": 20,
    "modality": "image",
    "model": "SD-v1-5",
    "params_B": 0.9,
    "run": 25
  },
  {
    "total_energy_j": 277.81,
    "avg_power_w": 20.29,
    "max_power_w": 26.62,
    "duration_sec": 13.26,
    "samples": 22,
    "generation_time_sec": 13.05,
    "resolution": "512x512",
    "steps": 20,
    "modality": "image",
    "model": "SD-v1-5",
    "params_B": 0.9,
    "run": 26
  },
  {
    "total_energy_j": 275.17,
    "avg_power_w": 20.21,
    "max_power_w": 25.67,
    "duration_sec": 13.17,
    "samples": 22,
    "generation_time_sec": 13.08,
    "resolution": "512x512",
    "steps": 20,
    "modality": "image",
    "model": "SD-v1-5",
    "params_B": 0.9,
    "run": 27
  },
  {
    "total_energy_j": 272.16,
    "avg_power_w": 20.65,
    "max_power_w": 23.03,
    "duration_sec": 12.91,
    "samples": 21,
    "generation_time_sec": 13.05,
    "resolution": "512x512",
    "steps": 20,
    "modality": "image",
    "model": "SD-v1-5",
    "params_B": 0.9,
    "run": 28
  },
  {
    "total_energy_j": 276.08,
    "avg_power_w": 20.32,
    "max_power_w": 24.67,
    "duration_sec": 13.21,
    "samples": 22,
    "generation_time_sec": 13.05,
    "resolution": "512x512",
    "steps": 20,
    "modality": "image",
    "model": "SD-v1-5",
    "params_B": 0.9,
    "run": 29
  },
  {
    "total_energy_j": 278.9,
    "avg_power_w": 20.04,
    "max_power_w": 24.9,
    "duration_sec": 13.38,
    "samples": 22,
    "generation_time_sec": 13.07,
    "resolution": "512x512",
    "steps": 20,
    "modality": "image",
    "model": "SD-v1-5",
    "params_B": 0.9,
    "run": 30
  },
  {
    "total_energy_j": 398.87,
    "avg_power_w": 20.93,
    "max_power_w": 22.22,
    "duration_sec": 18.78,
    "samples": 31,
    "generation_time_sec": 18.97,
    "resolution": "512x512",
    "steps": 30,
    "modality": "image",
    "model": "SD-v1-5",
    "params_B": 0.9,
    "run": 1
  },
  {
    "total_energy_j": 403.38,
    "avg_power_w": 20.83,
    "max_power_w": 24.16,
    "duration_sec": 18.95,
    "samples": 31,
    "generation_time_sec": 18.99,
    "resolution": "512x512",
    "steps": 30,
    "modality": "image",
    "model": "SD-v1-5",
    "params_B": 0.9,
    "run": 2
  },
  {
    "total_energy_j": 396.84,
    "avg_power_w": 21.16,
    "max_power_w": 23.29,
    "duration_sec": 18.52,
    "samples": 30,
    "generation_time_sec": 18.97,
    "resolution": "512x512",
    "steps": 30,
    "modality": "image",
    "model": "SD-v1-5",
    "params_B": 0.9,
    "run": 3
  },
  {
    "total_energy_j": 406.61,
    "avg_power_w": 20.6,
    "max_power_w": 25.48,
    "duration_sec": 19.26,
    "samples": 31,
    "generation_time_sec": 19.01,
    "resolution": "512x512",
    "steps": 30,
    "modality": "image",
    "model": "SD-v1-5",
    "params_B": 0.9,
    "run": 4
  },
  {
    "total_energy_j": 397.59,
    "avg_power_w": 21.31,
    "max_power_w": 25.38,
    "duration_sec": 18.6,
    "samples": 30,
    "generation_time_sec": 19.0,
    "resolution": "512x512",
    "steps": 30,
    "modality": "image",
    "model": "SD-v1-5",
    "params_B": 0.9,
    "run": 5
  },
  {
    "total_energy_j": 405.54,
    "avg_power_w": 20.92,
    "max_power_w": 23.47,
    "duration_sec": 19.01,
    "samples": 31,
    "generation_time_sec": 19.01,
    "resolution": "512x512",
    "steps": 30,
    "modality": "image",
    "model": "SD-v1-5",
    "params_B": 0.9,
    "run": 6
  },
  {
    "total_energy_j": 402.26,
    "avg_power_w": 21.01,
    "max_power_w": 22.54,
    "duration_sec": 18.87,
    "samples": 30,
    "generation_time_sec": 19.0,
    "resolution": "512x512",
    "steps": 30,
    "modality": "image",
    "model": "SD-v1-5",
    "params_B": 0.9,
    "run": 7
  },
  {
    "total_energy_j": 397.52,
    "avg_power_w": 21.19,
    "max_power_w": 26.21,
    "duration_sec": 18.64,
    "samples": 30,
    "generation_time_sec": 19.03,
    "resolution": "512x512",
    "steps": 30,
    "modality": "image",
    "model": "SD-v1-5",
    "params_B": 0.9,
    "run": 8
  },
  {
    "total_energy_j": 395.1,
    "avg_power_w": 20.95,
    "max_power_w": 23.53,
    "duration_sec": 18.58,
    "samples": 30,
    "generation_time_sec": 19.0,
    "resolution": "512x512",
    "steps": 30,
    "modality": "image",
    "model": "SD-v1-5",
    "params_B": 0.9,
    "run": 9
  },
  {
    "total_energy_j": 394.38,
    "avg_power_w": 21.22,
    "max_power_w": 25.48,
    "duration_sec": 18.53,
    "samples": 30,
    "generation_time_sec": 18.98,
    "resolution": "512x512",
    "steps": 30,
    "modality": "image",
    "model": "SD-v1-5",
    "params_B": 0.9,
    "run": 10
  },
  {
    "total_energy_j": 403.53,
    "avg_power_w": 20.84,
    "max_power_w": 24.58,
    "duration_sec": 19.04,
    "samples": 32,
    "generation_time_sec": 18.96,
    "resolution": "512x512",
    "steps": 30,
    "modality": "image",
    "model": "SD-v1-5",
    "params_B": 0.9,
    "run": 11
  },
  {
    "total_energy_j": 399.76,
    "avg_power_w": 20.96,
    "max_power_w": 22.21,
    "duration_sec": 18.83,
    "samples": 30,
    "generation_time_sec": 18.98,
    "resolution": "512x512",
    "steps": 30,
    "modality": "image",
    "model": "SD-v1-5",
    "params_B": 0.9,
    "run": 12
  },
  {
    "total_energy_j": 401.05,
    "avg_power_w": 20.98,
    "max_power_w": 23.2,
    "duration_sec": 18.88,
    "samples": 31,
    "generation_time_sec": 18.99,
    "resolution": "512x512",
    "steps": 30,
    "modality": "image",
    "model": "SD-v1-5",
    "params_B": 0.9,
    "run": 13
  },
  {
    "total_energy_j": 399.98,
    "avg_power_w": 20.9,
    "max_power_w": 23.5,
    "duration_sec": 18.89,
    "samples": 31,
    "generation_time_sec": 18.99,
    "resolution": "512x512",
    "steps": 30,
    "modality": "image",
    "model": "SD-v1-5",
    "params_B": 0.9,
    "run": 14
  },
  {
    "total_energy_j": 397.69,
    "avg_power_w": 21.02,
    "max_power_w": 23.83,
    "duration_sec": 18.64,
    "samples": 30,
    "generation_time_sec": 18.97,
    "resolution": "512x512",
    "steps": 30,
    "modality": "image",
    "model": "SD-v1-5",
    "params_B": 0.9,
    "run": 15
  },
  {
    "total_energy_j": 406.19,
    "avg_power_w": 20.66,
    "max_power_w": 24.93,
    "duration_sec": 19.18,
    "samples": 30,
    "generation_time_sec": 18.99,
    "resolution": "512x512",
    "steps": 30,
    "modality": "image",
    "model": "SD-v1-5",
    "params_B": 0.9,
    "run": 16
  },
  {
    "total_energy_j": 399.72,
    "avg_power_w": 21.17,
    "max_power_w": 25.26,
    "duration_sec": 18.71,
    "samples": 30,
    "generation_time_sec": 18.99,
    "resolution": "512x512",
    "steps": 30,
    "modality": "image",
    "model": "SD-v1-5",
    "params_B": 0.9,
    "run": 17
  },
  {
    "total_energy_j": 397.73,
    "avg_power_w": 20.96,
    "max_power_w": 23.42,
    "duration_sec": 18.67,
    "samples": 31,
    "generation_time_sec": 18.98,
    "resolution": "512x512",
    "steps": 30,
    "modality": "image",
    "model": "SD-v1-5",
    "params_B": 0.9,
    "run": 18
  },
  {
    "total_energy_j": 392.47,
    "avg_power_w": 21.24,
    "max_power_w": 24.25,
    "duration_sec": 18.33,
    "samples": 29,
    "generation_time_sec": 18.99,
    "resolution": "512x512",
    "steps": 30,
    "modality": "image",
    "model": "SD-v1-5",
    "params_B": 0.9,
    "run": 19
  },
  {
    "total_energy_j": 406.96,
    "avg_power_w": 20.5,
    "max_power_w": 25.17,
    "duration_sec": 19.26,
    "samples": 31,
    "generation_time_sec": 18.99,
    "resolution": "512x512",
    "steps": 30,
    "modality": "image",
    "model": "SD-v1-5",
    "params_B": 0.9,
    "run": 20
  },
  {
    "total_energy_j": 401.1,
    "avg_power_w": 20.91,
    "max_power_w": 23.16,
    "duration_sec": 18.9,
    "samples": 31,
    "generation_time_sec": 18.99,
    "resolution": "512x512",
    "steps": 30,
    "modality": "image",
    "model": "SD-v1-5",
    "params_B": 0.9,
    "run": 21
  },
  {
    "total_energy_j": 395.81,
    "avg_power_w": 21.08,
    "max_power_w": 25.02,
    "duration_sec": 18.64,
    "samples": 30,
    "generation_time_sec": 19.0,
    "resolution": "512x512",
    "steps": 30,
    "modality": "image",
    "model": "SD-v1-5",
    "params_B": 0.9,
    "run": 22
  },
  {
    "total_energy_j": 395.66,
    "avg_power_w": 21.28,
    "max_power_w": 25.73,
    "duration_sec": 18.54,
    "samples": 29,
    "generation_time_sec": 18.99,
    "resolution": "512x512",
    "steps": 30,
    "modality": "image",
    "model": "SD-v1-5",
    "params_B": 0.9,
    "run": 23
  },
  {
    "total_energy_j": 399.08,
    "avg_power_w": 20.89,
    "max_power_w": 24.05,
    "duration_sec": 18.86,
    "samples": 30,
    "generation_time_sec": 18.98,
    "resolution": "512x512",
    "steps": 30,
    "modality": "image",
    "model": "SD-v1-5",
    "params_B": 0.9,
    "run": 24
  },
  {
    "total_energy_j": 400.18,
    "avg_power_w": 20.98,
    "max_power_w": 22.72,
    "duration_sec": 18.82,
    "samples": 30,
    "generation_time_sec": 18.99,
    "resolution": "512x512",
    "steps": 30,
    "modality": "image",
    "model": "SD-v1-5",
    "params_B": 0.9,
    "run": 25
  },
  {
    "total_energy_j": 398.49,
    "avg_power_w": 21.08,
    "max_power_w": 23.26,
    "duration_sec": 18.73,
    "samples": 30,
    "generation_time_sec": 19.0,
    "resolution": "512x512",
    "steps": 30,
    "modality": "image",
    "model": "SD-v1-5",
    "params_B": 0.9,
    "run": 26
  },
  {
    "total_energy_j": 400.36,
    "avg_power_w": 21.02,
    "max_power_w": 22.27,
    "duration_sec": 18.8,
    "samples": 30,
    "generation_time_sec": 18.99,
    "resolution": "512x512",
    "steps": 30,
    "modality": "image",
    "model": "SD-v1-5",
    "params_B": 0.9,
    "run": 27
  },
  {
    "total_energy_j": 399.58,
    "avg_power_w": 21.18,
    "max_power_w": 25.67,
    "duration_sec": 18.67,
    "samples": 30,
    "generation_time_sec": 19.0,
    "resolution": "512x512",
    "steps": 30,
    "modality": "image",
    "model": "SD-v1-5",
    "params_B": 0.9,
    "run": 28
  },
  {
    "total_energy_j": 403.07,
    "avg_power_w": 20.67,
    "max_power_w": 24.82,
    "duration_sec": 19.1,
    "samples": 31,
    "generation_time_sec": 19.0,
    "resolution": "512x512",
    "steps": 30,
    "modality": "image",
    "model": "SD-v1-5",
    "params_B": 0.9,
    "run": 29
  },
  {
    "total_energy_j": 394.32,
    "avg_power_w": 21.35,
    "max_power_w": 24.17,
    "duration_sec": 18.35,
    "samples": 30,
    "generation_time_sec": 18.98,
    "resolution": "512x512",
    "steps": 30,
    "modality": "image",
    "model": "SD-v1-5",
    "params_B": 0.9,
    "run": 30
  }
]